{"data": {"user": {"result": {"__typename": "User", "timeline": {"timeline": {"instructions": [{"type": "TimelineAddEntries", "entries": [{"entryId": "user-59241059", "sortIndex": "1725702210483911768", "content": {"entryType": "TimelineTimelineItem", "__typename": "TimelineTimelineItem", "itemContent": {"itemType": "TimelineUser", "__typename": "TimelineUser", "user_results": {"result": {"__typename": "User", "id": "VXNlcjo1OTI0MTA1OQ==", "rest_id": "59241059", "affiliates_highlighted_label": {}, "has_graduated_access": true, "is_blue_verified": false, "profile_image_shape": "Circle", "legacy": {"can_dm": false, "can_media_tag": true, "created_at": "Wed Jul 22 20:35:47 +0000 2009", "default_profile": false, "default_profile_image": false, "description": "Sr. VP/Editor-in-Chief of @BlackEnterprise Magazine. Award-winning author. Co-founder, Milestone Media comic book co. Proud alum of Norfolk State U.", "entities": {"description": {"urls": []}, "url": {"urls": [{"display_url": "blackenterprise.com/bios/derek-din\u2026", "expanded_url": "http://www.blackenterprise.com/bios/derek-dingle", "url": "http://t.co/2wXxw2nKwB", "indices": [0, 22]}]}}, "fast_followers_count": 0, "favourites_count": 296, "followers_count": 9631, "friends_count": 988, "has_custom_timelines": false, "is_translator": false, "listed_count": 296, "location": "New York", "media_count": 565, "name": "Derek T. Dingle", "normal_followers_count": 9631, "pinned_tweet_ids_str": ["1249214230190084102"], "possibly_sensitive": false, "profile_banner_url": "https://pbs.twimg.com/profile_banners/59241059/1586900200", "profile_image_url_https": "https://pbs.twimg.com/profile_images/326957627/Derek_normal.jpg", "profile_interstitial_type": "", "screen_name": "DTDingle", "statuses_count": 17324, "translator_type": "none", "url": "http://t.co/2wXxw2nKwB", "verified": false, "want_retweets": false, "withheld_in_countries": []}}}, "userDisplayType": "User"}, "clientEventInfo": {"component": "FollowingSgs", "element": "user"}}}, {"entryId": "user-163087021", "sortIndex": "1725702210483911767", "content": {"entryType": "TimelineTimelineItem", "__typename": "TimelineTimelineItem", "itemContent": {"itemType": "TimelineUser", "__typename": "TimelineUser", "user_results": {"result": {"__typename": "User", "id": "VXNlcjoxNjMwODcwMjE=", "rest_id": "163087021", "affiliates_highlighted_label": {}, "has_graduated_access": true, "is_blue_verified": false, "profile_image_shape": "Circle", "legacy": {"can_dm": false, "can_media_tag": true, "created_at": "Mon Jul 05 14:27:42 +0000 2010", "default_profile": false, "default_profile_image": false, "description": "Writer and occasional data dabbler. Covering science, health and education for Business Day", "entities": {"description": {"urls": []}, "url": {"urls": [{"display_url": "businesslive.co.za", "expanded_url": "http://www.businesslive.co.za", "url": "https://t.co/tnB6LCvzqQ", "indices": [0, 23]}]}}, "fast_followers_count": 0, "favourites_count": 57, "followers_count": 2372, "friends_count": 863, "has_custom_timelines": false, "is_translator": false, "listed_count": 59, "location": "Cape Town", "media_count": 5, "name": "Tamar Kahn", "normal_followers_count": 2372, "pinned_tweet_ids_str": [], "possibly_sensitive": false, "profile_banner_url": "https://pbs.twimg.com/profile_banners/163087021/1655133236", "profile_image_url_https": "https://pbs.twimg.com/profile_images/432883572894998528/_51E08wP_normal.jpeg", "profile_interstitial_type": "", "screen_name": "TamarKahn", "statuses_count": 1970, "translator_type": "none", "url": "https://t.co/tnB6LCvzqQ", "verified": false, "want_retweets": false, "withheld_in_countries": []}}}, "userDisplayType": "User"}, "clientEventInfo": {"component": "FollowingSgs", "element": "user"}}}, {"entryId": "user-994638114", "sortIndex": "1725702210483911766", "content": {"entryType": "TimelineTimelineItem", "__typename": "TimelineTimelineItem", "itemContent": {"itemType": "TimelineUser", "__typename": "TimelineUser", "user_results": {"result": {"__typename": "User", "id": "VXNlcjo5OTQ2MzgxMTQ=", "rest_id": "994638114", "affiliates_highlighted_label": {}, "has_graduated_access": true, "is_blue_verified": false, "profile_image_shape": "Circle", "legacy": {"can_dm": false, "can_media_tag": true, "created_at": "Fri Dec 07 08:50:49 +0000 2012", "default_profile": false, "default_profile_image": false, "description": "Correspondent for @TIME. Ex-China Bureau Chief, gratefully reunited with Southeast Asia. Audere est Facere.", "entities": {"description": {"urls": []}, "url": {"urls": [{"display_url": "time.com", "expanded_url": "http://www.time.com", "url": "https://t.co/N93ZjUmoir", "indices": [0, 23]}]}}, "fast_followers_count": 0, "favourites_count": 831, "followers_count": 7161, "friends_count": 953, "has_custom_timelines": true, "is_translator": false, "listed_count": 232, "location": "Singapore", "media_count": 621, "name": "Charlie Campbell", "normal_followers_count": 7161, "pinned_tweet_ids_str": [], "possibly_sensitive": false, "profile_banner_url": "https://pbs.twimg.com/profile_banners/994638114/1389165167", "profile_image_url_https": "https://pbs.twimg.com/profile_images/473840190037848065/7QITZR_o_normal.jpeg", "profile_interstitial_type": "", "screen_name": "CharlieCamp6ell", "statuses_count": 3013, "translator_type": "none", "url": "https://t.co/N93ZjUmoir", "verified": false, "want_retweets": false, "withheld_in_countries": []}}}, "userDisplayType": "User"}, "clientEventInfo": {"component": "FollowingSgs", "element": "user"}}}, {"entryId": "user-1032055435", "sortIndex": "1725702210483911765", "content": {"entryType": "TimelineTimelineItem", "__typename": "TimelineTimelineItem", "itemContent": {"itemType": "TimelineUser", "__typename": "TimelineUser", "user_results": {"result": {"__typename": "User", "id": "VXNlcjoxMDMyMDU1NDM1", "rest_id": "1032055435", "affiliates_highlighted_label": {}, "has_graduated_access": true, "is_blue_verified": false, "profile_image_shape": "Circle", "legacy": {"can_dm": false, "can_media_tag": false, "created_at": "Mon Dec 24 06:08:20 +0000 2012", "default_profile": false, "default_profile_image": false, "description": "Passionate about writing. Love experimenting. Music enthusiast.", "entities": {"description": {"urls": []}}, "fast_followers_count": 0, "favourites_count": 915, "followers_count": 1511, "friends_count": 377, "has_custom_timelines": false, "is_translator": false, "listed_count": 41, "location": "Bangalore, India", "media_count": 25, "name": "Sneha Shankar", "normal_followers_count": 1511, "pinned_tweet_ids_str": [], "possibly_sensitive": false, "profile_banner_url": "https://pbs.twimg.com/profile_banners/1032055435/1568782877", "profile_image_url_https": "https://pbs.twimg.com/profile_images/1666827547462746113/5g41XQnR_normal.jpg", "profile_interstitial_type": "", "screen_name": "SnehaShankar30", "statuses_count": 2041, "translator_type": "none", "verified": false, "want_retweets": false, "withheld_in_countries": []}}}, "userDisplayType": "User"}, "clientEventInfo": {"component": "FollowingSgs", "element": "user"}}}, {"entryId": "user-2397479856", "sortIndex": "1725702210483911764", "content": {"entryType": "TimelineTimelineItem", "__typename": "TimelineTimelineItem", "itemContent": {"itemType": "TimelineUser", "__typename": "TimelineUser", "user_results": {"result": {"__typename": "User", "id": "VXNlcjoyMzk3NDc5ODU2", "rest_id": "2397479856", "affiliates_highlighted_label": {}, "has_graduated_access": true, "is_blue_verified": false, "profile_image_shape": "Circle", "legacy": {"can_dm": false, "can_media_tag": true, "created_at": "Wed Mar 19 08:09:04 +0000 2014", "default_profile": false, "default_profile_image": false, "description": "director of WHITE NOISE | formerly @theatlantic | now senior producer @newyorker | usually eating uzbek food in queens", "entities": {"description": {"urls": []}, "url": {"urls": [{"display_url": "daniellombroso.com", "expanded_url": "http://www.daniellombroso.com/", "url": "https://t.co/2cFOIQTpcx", "indices": [0, 23]}]}}, "fast_followers_count": 0, "favourites_count": 4223, "followers_count": 3417, "friends_count": 1125, "has_custom_timelines": true, "is_translator": false, "listed_count": 62, "location": "nyc", "media_count": 74, "name": "Daniel Lombroso", "normal_followers_count": 3417, "pinned_tweet_ids_str": [], "possibly_sensitive": false, "profile_banner_url": "https://pbs.twimg.com/profile_banners/2397479856/1624141029", "profile_image_url_https": "https://pbs.twimg.com/profile_images/1608135835689304064/BDcoTyhs_normal.jpg", "profile_interstitial_type": "", "screen_name": "DanielLombroso", "statuses_count": 662, "translator_type": "none", "url": "https://t.co/2cFOIQTpcx", "verified": false, "want_retweets": false, "withheld_in_countries": []}}}, "userDisplayType": "User"}, "clientEventInfo": {"component": "FollowingSgs", "element": "user"}}}, {"entryId": "user-27245649", "sortIndex": "1725702210483911763", "content": {"entryType": "TimelineTimelineItem", "__typename": "TimelineTimelineItem", "itemContent": {"itemType": "TimelineUser", "__typename": "TimelineUser", "user_results": {"result": {"__typename": "User", "id": "VXNlcjoyNzI0NTY0OQ==", "rest_id": "27245649", "affiliates_highlighted_label": {}, "has_graduated_access": true, "is_blue_verified": false, "profile_image_shape": "Circle", "legacy": {"can_dm": false, "can_media_tag": true, "created_at": "Sat Mar 28 15:21:21 +0000 2009", "default_profile": false, "default_profile_image": false, "description": "Visiting Professor at Korea University. Former Executive Editor and Asia Editor @Reuters.", "entities": {"description": {"urls": []}, "url": {"urls": [{"display_url": "twitter.com/TheJeanYoon", "expanded_url": "https://twitter.com/TheJeanYoon", "url": "https://t.co/vRuBxncSIz", "indices": [0, 23]}]}}, "fast_followers_count": 0, "favourites_count": 1305, "followers_count": 4381, "friends_count": 1348, "has_custom_timelines": true, "is_translator": false, "listed_count": 218, "location": "Seoul, Republic of Korea", "media_count": 44, "name": "Jean Yoon \uc724\ud654\uc9c4", "normal_followers_count": 4381, "pinned_tweet_ids_str": [], "possibly_sensitive": false, "profile_image_url_https": "https://pbs.twimg.com/profile_images/718403130132549633/ejNfBG7O_normal.jpg", "profile_interstitial_type": "", "screen_name": "TheJeanYoon", "statuses_count": 9633, "translator_type": "none", "url": "https://t.co/vRuBxncSIz", "verified": false, "want_retweets": false, "withheld_in_countries": []}}}, "userDisplayType": "User"}, "clientEventInfo": {"component": "FollowingSgs", "element": "user"}}}, {"entryId": "user-142033532", "sortIndex": "1725702210483911762", "content": {"entryType": "TimelineTimelineItem", "__typename": "TimelineTimelineItem", "itemContent": {"itemType": "TimelineUser", "__typename": "TimelineUser", "user_results": {"result": {"__typename": "User", "id": "VXNlcjoxNDIwMzM1MzI=", "rest_id": "142033532", "affiliates_highlighted_label": {}, "has_graduated_access": true, "is_blue_verified": false, "profile_image_shape": "Circle", "legacy": {"can_dm": true, "can_media_tag": true, "created_at": "Sun May 09 19:09:55 +0000 2010", "default_profile": false, "default_profile_image": false, "description": "Editor Investigation @HumNewsPakistan.Worked @SamaaTV @GeoNews_urdu @WashingtonPost @CNN @TheNews_Intl @ETribune @McClatchyDC @The_Nation @KcStar,ICFJ,GIZ,SAARC", "entities": {"description": {"urls": []}, "url": {"urls": [{"display_url": "washingtonpost.com/newssearch/?qu\u2026", "expanded_url": "https://www.washingtonpost.com/newssearch/?query=zahid+gishkori", "url": "https://t.co/3kE0c93cFn", "indices": [0, 23]}]}}, "fast_followers_count": 0, "favourites_count": 21061, "followers_count": 112990, "friends_count": 9244, "has_custom_timelines": true, "is_translator": false, "listed_count": 209, "location": "Pakistan\ud83c\uddf5\ud83c\uddf0 \ud83d\udc96", "media_count": 4687, "name": "Zahid Gishkori", "normal_followers_count": 112990, "pinned_tweet_ids_str": ["1653062053844733953"], "possibly_sensitive": false, "profile_banner_url": "https://pbs.twimg.com/profile_banners/142033532/1404914164", "profile_image_url_https": "https://pbs.twimg.com/profile_images/1719750520007426049/zNnZaUDP_normal.jpg", "profile_interstitial_type": "", "screen_name": "ZahidGishkori", "statuses_count": 40381, "translator_type": "regular", "url": "https://t.co/3kE0c93cFn", "verified": false, "want_retweets": false, "withheld_in_countries": []}, "professional": {"rest_id": "1549236199444959235", "professional_type": "Creator", "category": [{"id": 580, "name": "Media & News Company", "icon_name": "IconBriefcaseStroke"}]}}}, "userDisplayType": "User"}, "clientEventInfo": {"component": "FollowingSgs", "element": "user"}}}, {"entryId": "user-76966092", "sortIndex": "1725702210483911761", "content": {"entryType": "TimelineTimelineItem", "__typename": "TimelineTimelineItem", "itemContent": {"itemType": "TimelineUser", "__typename": "TimelineUser", "user_results": {"result": {"__typename": "User", "id": "VXNlcjo3Njk2NjA5Mg==", "rest_id": "76966092", "affiliates_highlighted_label": {}, "has_graduated_access": true, "is_blue_verified": true, "profile_image_shape": "Circle", "legacy": {"can_dm": false, "can_media_tag": true, "created_at": "Thu Sep 24 15:31:23 +0000 2009", "default_profile": false, "default_profile_image": false, "description": "\ud83d\udca1 Entrepreneur Magazine \ud83d\udcb0 Top Marketing Leader \n\u2764\ufe0f Founder \ud83d\udcc6 @Calendar & \ud83d\udcb2@Due \n\ud83d\udcc8 Nations #1 Connector", "entities": {"description": {"urls": []}, "url": {"urls": [{"display_url": "linkedin.com/in/johnrampton/", "expanded_url": "https://www.linkedin.com/in/johnrampton/", "url": "https://t.co/r0oXSWnK25", "indices": [0, 23]}]}}, "fast_followers_count": 0, "favourites_count": 19206, "followers_count": 1206959, "friends_count": 554931, "has_custom_timelines": true, "is_translator": false, "listed_count": 6432, "location": "Salt Lake City, UT", "media_count": 18365, "name": "John Rampton", "normal_followers_count": 1206959, "pinned_tweet_ids_str": [], "possibly_sensitive": false, "profile_image_url_https": "https://pbs.twimg.com/profile_images/1706072496653717504/FC9Bxml-_normal.jpg", "profile_interstitial_type": "", "screen_name": "johnrampton", "statuses_count": 40941, "translator_type": "none", "url": "https://t.co/r0oXSWnK25", "verified": false, "want_retweets": false, "withheld_in_countries": []}, "professional": {"rest_id": "1503832588837744642", "professional_type": "Business", "category": [{"id": 192, "name": "Financial Services", "icon_name": "IconBriefcaseStroke"}]}}}, "userDisplayType": "User"}, "clientEventInfo": {"component": "FollowingSgs", "element": "user"}}}, {"entryId": "user-213539531", "sortIndex": "1725702210483911760", "content": {"entryType": "TimelineTimelineItem", "__typename": "TimelineTimelineItem", "itemContent": {"itemType": "TimelineUser", "__typename": "TimelineUser", "user_results": {"result": {"__typename": "User", "id": "VXNlcjoyMTM1Mzk1MzE=", "rest_id": "213539531", "affiliates_highlighted_label": {}, "has_graduated_access": true, "is_blue_verified": true, "profile_image_shape": "Circle", "legacy": {"can_dm": false, "can_media_tag": true, "created_at": "Tue Nov 09 04:59:38 +0000 2010", "default_profile": false, "default_profile_image": false, "description": "Journalist survived bombs & bullets.Fighting censorship.Banned 3 times in Pakistan.Working with https://t.co/v4aM9V1A2u & https://t.co/Hzd6938PEc", "entities": {"description": {"urls": [{"display_url": "geo.tv", "expanded_url": "http://geo.tv", "url": "https://t.co/v4aM9V1A2u", "indices": [96, 119]}, {"display_url": "washingtonpost.com/people/hamid-m\u2026", "expanded_url": "https://www.washingtonpost.com/people/hamid-mir/", "url": "https://t.co/Hzd6938PEc", "indices": [122, 145]}]}, "url": {"urls": [{"display_url": "youtube.com/@HamidMirOffic\u2026", "expanded_url": "http://youtube.com/@HamidMirOfficial", "url": "https://t.co/V3ck5BWRH4", "indices": [0, 23]}]}}, "fast_followers_count": 0, "favourites_count": 537, "followers_count": 8247798, "friends_count": 610, "has_custom_timelines": true, "is_translator": false, "listed_count": 4309, "location": "Islamabad, Pakistan", "media_count": 5973, "name": "Hamid Mir \u062d\u0627\u0645\u062f \u0645\u06cc\u0631", "normal_followers_count": 8247798, "pinned_tweet_ids_str": ["1724824580001243341"], "possibly_sensitive": false, "profile_banner_url": "https://pbs.twimg.com/profile_banners/213539531/1645988378", "profile_image_url_https": "https://pbs.twimg.com/profile_images/1151556274364067847/C71zAsVy_normal.png", "profile_interstitial_type": "", "screen_name": "HamidMirPAK", "statuses_count": 46765, "translator_type": "regular", "url": "https://t.co/V3ck5BWRH4", "verified": false, "want_retweets": false, "withheld_in_countries": []}}}, "userDisplayType": "User"}, "clientEventInfo": {"component": "FollowingSgs", "element": "user"}}}, {"entryId": "user-2791565088", "sortIndex": "1725702210483911759", "content": {"entryType": "TimelineTimelineItem", "__typename": "TimelineTimelineItem", "itemContent": {"itemType": "TimelineUser", "__typename": "TimelineUser", "user_results": {"result": {"__typename": "User", "id": "VXNlcjoyNzkxNTY1MDg4", "rest_id": "2791565088", "affiliates_highlighted_label": {"label": {"url": {"url": "https://twitter.com/IsraelMFA", "urlType": "DeepLink"}, "badge": {"url": "https://pbs.twimg.com/profile_images/1587900251540791304/OwWylh5s_bigger.jpg"}, "description": "Israel Foreign Ministry", "userLabelType": "BusinessLabel", "userLabelDisplayType": "Badge"}}, "has_graduated_access": true, "is_blue_verified": true, "profile_image_shape": "Circle", "legacy": {"can_dm": true, "can_media_tag": true, "created_at": "Fri Sep 05 10:11:19 +0000 2014", "default_profile": true, "default_profile_image": false, "description": "Ambassador of Israel to Sweden / Israels ambassad\u00f6r i Sverige / \u05e9\u05d2\u05e8\u05d9\u05e8 \u05d9\u05e9\u05e8\u05d0\u05dc \u05d1\u05e9\u05d5\u05d5\u05d3\u05d9\u05d4 / \u0633\u0641\u064a\u0631 \u0625\u0633\u0631\u0627\u0626\u064a\u0644 \u0641\u064a \u0627\u0644\u0633\u0648\u064a\u062f", "entities": {"description": {"urls": []}}, "fast_followers_count": 0, "favourites_count": 2801, "followers_count": 10840, "friends_count": 546, "has_custom_timelines": true, "is_translator": false, "listed_count": 108, "location": "Stockholm, Sweden", "media_count": 817, "name": "Ziv Nevo Kulman \ud83c\uddee\ud83c\uddf1\ud83c\udf97\ufe0f", "normal_followers_count": 10840, "pinned_tweet_ids_str": ["1446176674576535560"], "possibly_sensitive": false, "profile_banner_url": "https://pbs.twimg.com/profile_banners/2791565088/1679930519", "profile_image_url_https": "https://pbs.twimg.com/profile_images/1425001502867873801/cezx09Bs_normal.jpg", "profile_interstitial_type": "", "screen_name": "zivnk", "statuses_count": 4134, "translator_type": "none", "verified": false, "verified_type": "Government", "want_retweets": false, "withheld_in_countries": []}}}, "userDisplayType": "User"}, "clientEventInfo": {"component": "FollowingSgs", "element": "user"}}}, {"entryId": "user-65647594", "sortIndex": "1725702210483911758", "content": {"entryType": "TimelineTimelineItem", "__typename": "TimelineTimelineItem", "itemContent": {"itemType": "TimelineUser", "__typename": "TimelineUser", "user_results": {"result": {"__typename": "User", "id": "VXNlcjo2NTY0NzU5NA==", "rest_id": "65647594", "affiliates_highlighted_label": {}, "has_graduated_access": true, "is_blue_verified": true, "profile_image_shape": "Circle", "legacy": {"can_dm": false, "can_media_tag": true, "created_at": "Fri Aug 14 14:31:39 +0000 2009", "default_profile": false, "default_profile_image": false, "description": "Former NASA Astronaut & US Navy Captain Inquires: Keppler Speakers or United Talent Agency Husband to @amikokauderer, Brother of @SenMarkKelly", "entities": {"description": {"urls": []}, "url": {"urls": [{"display_url": "linktr.ee/StationCDRKelly", "expanded_url": "https://linktr.ee/StationCDRKelly", "url": "https://t.co/1BJNTjuRSn", "indices": [0, 23]}]}}, "fast_followers_count": 0, "favourites_count": 2656, "followers_count": 5207398, "friends_count": 758, "has_custom_timelines": true, "is_translator": false, "listed_count": 8137, "location": "Denver, CO", "media_count": 2452, "name": "Scott Kelly", "normal_followers_count": 5207398, "pinned_tweet_ids_str": [], "possibly_sensitive": false, "profile_banner_url": "https://pbs.twimg.com/profile_banners/65647594/1643333844", "profile_image_url_https": "https://pbs.twimg.com/profile_images/1614931772936187908/pjOGL4U__normal.jpg", "profile_interstitial_type": "", "screen_name": "StationCDRKelly", "statuses_count": 5157, "translator_type": "none", "url": "https://t.co/1BJNTjuRSn", "verified": false, "want_retweets": false, "withheld_in_countries": []}, "professional": {"rest_id": "1476294583273197570", "professional_type": "Creator", "category": [{"id": 713, "name": "Science & Technology", "icon_name": "IconBriefcaseStroke"}]}}}, "userDisplayType": "User"}, "clientEventInfo": {"component": "FollowingSgs", "element": "user"}}}, {"entryId": "user-1451773004", "sortIndex": "1725702210483911757", "content": {"entryType": "TimelineTimelineItem", "__typename": "TimelineTimelineItem", "itemContent": {"itemType": "TimelineUser", "__typename": "TimelineUser", "user_results": {"result": {"__typename": "User", "id": "VXNlcjoxNDUxNzczMDA0", "rest_id": "1451773004", "affiliates_highlighted_label": {"label": {"url": {"url": "https://twitter.com/NASA", "urlType": "DeepLink"}, "badge": {"url": "https://pbs.twimg.com/profile_images/1321163587679784960/0ZxKlEKB_bigger.jpg"}, "description": "NASA", "userLabelType": "BusinessLabel", "userLabelDisplayType": "Badge"}}, "has_graduated_access": true, "is_blue_verified": true, "profile_image_shape": "Square", "legacy": {"can_dm": false, "can_media_tag": true, "created_at": "Thu May 23 15:25:28 +0000 2013", "default_profile": false, "default_profile_image": false, "description": "NASA's page for the latest updates from the International Space Station. For the newest science, follow @ISS_Research. Verification: https://t.co/jSJ1pgS2xl", "entities": {"description": {"urls": [{"display_url": "nasa.gov/socialmedia", "expanded_url": "http://nasa.gov/socialmedia", "url": "https://t.co/jSJ1pgS2xl", "indices": [133, 156]}]}, "url": {"urls": [{"display_url": "nasa.gov/station", "expanded_url": "http://www.nasa.gov/station", "url": "https://t.co/DOiPSGj1vj", "indices": [0, 23]}]}}, "fast_followers_count": 0, "favourites_count": 22956, "followers_count": 8097196, "friends_count": 182, "has_custom_timelines": true, "is_translator": false, "listed_count": 17308, "location": "Low Earth Orbit", "media_count": 7614, "name": "International Space Station", "normal_followers_count": 8097196, "pinned_tweet_ids_str": [], "possibly_sensitive": false, "profile_banner_url": "https://pbs.twimg.com/profile_banners/1451773004/1643308708", "profile_image_url_https": "https://pbs.twimg.com/profile_images/1189945624583720960/k6MtoeIt_normal.jpg", "profile_interstitial_type": "", "screen_name": "Space_Station", "statuses_count": 17343, "translator_type": "none", "url": "https://t.co/DOiPSGj1vj", "verified": false, "verified_type": "Government", "want_retweets": false, "withheld_in_countries": []}}}, "userDisplayType": "User"}, "clientEventInfo": {"component": "FollowingSgs", "element": "user"}}}, {"entryId": "user-1899984391", "sortIndex": "1725702210483911756", "content": {"entryType": "TimelineTimelineItem", "__typename": "TimelineTimelineItem", "itemContent": {"itemType": "TimelineUser", "__typename": "TimelineUser", "user_results": {"result": {"__typename": "User", "id": "VXNlcjoxODk5OTg0Mzkx", "rest_id": "1899984391", "affiliates_highlighted_label": {}, "has_graduated_access": true, "is_blue_verified": true, "profile_image_shape": "Square", "legacy": {"can_dm": false, "can_media_tag": true, "created_at": "Tue Sep 24 10:12:31 +0000 2013", "default_profile": false, "default_profile_image": false, "description": "Mission of the People's Republic of China to the EU \ud83c\udde8\ud83c\uddf3\ud83c\uddea\ud83c\uddfa. Tweeting about #ChinaEU relations.", "entities": {"description": {"urls": []}, "url": {"urls": [{"display_url": "chinamission.be/eng/", "expanded_url": "http://www.chinamission.be/eng/", "url": "https://t.co/zN2qjEGKBp", "indices": [0, 23]}]}}, "fast_followers_count": 0, "favourites_count": 3772, "followers_count": 26040, "friends_count": 1940, "has_custom_timelines": true, "is_translator": false, "listed_count": 482, "location": "Brussels, Belgium", "media_count": 6627, "name": "Mission of China to the EU", "normal_followers_count": 26040, "pinned_tweet_ids_str": [], "possibly_sensitive": false, "profile_banner_url": "https://pbs.twimg.com/profile_banners/1899984391/1586067456", "profile_image_url_https": "https://pbs.twimg.com/profile_images/1246683282143666177/vFp-UtJ4_normal.jpg", "profile_interstitial_type": "", "screen_name": "ChinaEUMission", "statuses_count": 15024, "translator_type": "none", "url": "https://t.co/zN2qjEGKBp", "verified": false, "verified_type": "Government", "want_retweets": false, "withheld_in_countries": []}}}, "userDisplayType": "User"}, "clientEventInfo": {"component": "FollowingSgs", "element": "user"}}}, {"entryId": "user-1003537712", "sortIndex": "1725702210483911755", "content": {"entryType": "TimelineTimelineItem", "__typename": "TimelineTimelineItem", "itemContent": {"itemType": "TimelineUser", "__typename": "TimelineUser", "user_results": {"result": {"__typename": "User", "id": "VXNlcjoxMDAzNTM3NzEy", "rest_id": "1003537712", "affiliates_highlighted_label": {}, "has_graduated_access": true, "is_blue_verified": false, "profile_image_shape": "Circle", "legacy": {"can_dm": false, "can_media_tag": true, "created_at": "Tue Dec 11 07:36:50 +0000 2012", "default_profile": true, "default_profile_image": false, "description": "British diplomat. Former UK Ambassador to Libya, Iran, Qatar and Yemen", "entities": {"description": {"urls": []}, "url": {"urls": [{"display_url": "gov.uk/government/wor\u2026", "expanded_url": "http://www.gov.uk/government/world/qatar", "url": "https://t.co/wdlAw7ziWS", "indices": [0, 23]}]}}, "fast_followers_count": 0, "favourites_count": 713, "followers_count": 10643, "friends_count": 2781, "has_custom_timelines": true, "is_translator": false, "listed_count": 141, "location": "United Kingdom", "media_count": 190, "name": "Nicholas Hopton", "normal_followers_count": 10643, "pinned_tweet_ids_str": [], "possibly_sensitive": false, "profile_image_url_https": "https://pbs.twimg.com/profile_images/1462916536629399552/5CHQnzsE_normal.jpg", "profile_interstitial_type": "", "screen_name": "NicholasHopton", "statuses_count": 3600, "translator_type": "none", "url": "https://t.co/wdlAw7ziWS", "verified": false, "want_retweets": false, "withheld_in_countries": []}}}, "userDisplayType": "User"}, "clientEventInfo": {"component": "FollowingSgs", "element": "user"}}}, {"entryId": "user-100399816", "sortIndex": "1725702210483911754", "content": {"entryType": "TimelineTimelineItem", "__typename": "TimelineTimelineItem", "itemContent": {"itemType": "TimelineUser", "__typename": "TimelineUser", "user_results": {"result": {"__typename": "User", "id": "VXNlcjoxMDAzOTk4MTY=", "rest_id": "100399816", "affiliates_highlighted_label": {}, "has_graduated_access": true, "is_blue_verified": false, "profile_image_shape": "Circle", "legacy": {"can_dm": false, "can_media_tag": true, "created_at": "Wed Dec 30 04:10:34 +0000 2009", "default_profile": false, "default_profile_image": false, "description": "Business and crypto reporter @CNN. Lead writer of the CNN Business Nightcap newsletter. Low-key expert on cults. Formerly @WSJ", "entities": {"description": {"urls": []}, "url": {"urls": [{"display_url": "cnn.it/3rGaLcE", "expanded_url": "https://cnn.it/3rGaLcE", "url": "https://t.co/Gp7IHvk3a6", "indices": [0, 23]}]}}, "fast_followers_count": 0, "favourites_count": 2331, "followers_count": 2776, "friends_count": 1466, "has_custom_timelines": true, "is_translator": false, "listed_count": 119, "location": "Brooklyn, NY", "media_count": 110, "name": "Allison Morrow", "normal_followers_count": 2776, "pinned_tweet_ids_str": ["1299078604605792258"], "possibly_sensitive": false, "profile_banner_url": "https://pbs.twimg.com/profile_banners/100399816/1397061759", "profile_image_url_https": "https://pbs.twimg.com/profile_images/826144907765112832/JtMHfO7s_normal.jpg", "profile_interstitial_type": "", "screen_name": "allisondmorrow", "statuses_count": 1300, "translator_type": "none", "url": "https://t.co/Gp7IHvk3a6", "verified": false, "want_retweets": false, "withheld_in_countries": []}}}, "userDisplayType": "User"}, "clientEventInfo": {"component": "FollowingSgs", "element": "user"}}}, {"entryId": "user-21810329", "sortIndex": "1725702210483911753", "content": {"entryType": "TimelineTimelineItem", "__typename": "TimelineTimelineItem", "itemContent": {"itemType": "TimelineUser", "__typename": "TimelineUser", "user_results": {"result": {"__typename": "User", "id": "VXNlcjoyMTgxMDMyOQ==", "rest_id": "21810329", "affiliates_highlighted_label": {}, "has_graduated_access": true, "is_blue_verified": false, "profile_image_shape": "Circle", "legacy": {"can_dm": true, "can_media_tag": true, "created_at": "Tue Feb 24 23:10:17 +0000 2009", "default_profile": true, "default_profile_image": false, "description": "Senior writer, Bloomberg @economics. Ex @FT. Aussie. Red Sox nation. RTs not endorsements. sdonnan@bloomberg.net @sdonnan@journa.host", "entities": {"description": {"urls": []}}, "fast_followers_count": 0, "favourites_count": 19732, "followers_count": 31679, "friends_count": 10263, "has_custom_timelines": true, "is_translator": false, "listed_count": 1120, "location": "Washington DC", "media_count": 2993, "name": "Shawn Donnan", "normal_followers_count": 31679, "pinned_tweet_ids_str": ["1676756776849383430"], "possibly_sensitive": false, "profile_banner_url": "https://pbs.twimg.com/profile_banners/21810329/1595438548", "profile_image_url_https": "https://pbs.twimg.com/profile_images/1285988259743571968/h6zTgUPP_normal.jpg", "profile_interstitial_type": "", "screen_name": "sdonnan", "statuses_count": 173540, "translator_type": "none", "verified": false, "want_retweets": false, "withheld_in_countries": []}}}, "userDisplayType": "User"}, "clientEventInfo": {"component": "FollowingSgs", "element": "user"}}}, {"entryId": "user-161813561", "sortIndex": "1725702210483911752", "content": {"entryType": "TimelineTimelineItem", "__typename": "TimelineTimelineItem", "itemContent": {"itemType": "TimelineUser", "__typename": "TimelineUser", "user_results": {"result": {"__typename": "User", "id": "VXNlcjoxNjE4MTM1NjE=", "rest_id": "161813561", "affiliates_highlighted_label": {}, "has_graduated_access": true, "is_blue_verified": false, "profile_image_shape": "Circle", "legacy": {"can_dm": true, "can_media_tag": false, "created_at": "Thu Jul 01 21:18:13 +0000 2010", "default_profile": false, "default_profile_image": false, "description": "Beijing bureau chief for The New York Times. Living and reporting in mainland China for past seven years. R/tw not endorsements", "entities": {"description": {"urls": []}, "url": {"urls": [{"display_url": "nytimes.com/by/keith-brads\u2026", "expanded_url": "http://www.nytimes.com/by/keith-bradsher", "url": "https://t.co/1jhxBVd8pS", "indices": [0, 23]}]}}, "fast_followers_count": 0, "favourites_count": 2574, "followers_count": 37635, "friends_count": 1232, "has_custom_timelines": false, "is_translator": false, "listed_count": 1120, "location": "Beijing", "media_count": 440, "name": "Keith Bradsher", "normal_followers_count": 37635, "pinned_tweet_ids_str": [], "possibly_sensitive": false, "profile_image_url_https": "https://pbs.twimg.com/profile_images/1204563453/Keith_Twitter_Pic_v01_normal.JPG", "profile_interstitial_type": "", "screen_name": "KeithBradsher", "statuses_count": 10167, "translator_type": "none", "url": "https://t.co/1jhxBVd8pS", "verified": false, "want_retweets": false, "withheld_in_countries": []}}}, "userDisplayType": "User"}, "clientEventInfo": {"component": "FollowingSgs", "element": "user"}}}, {"entryId": "user-66673916", "sortIndex": "1725702210483911751", "content": {"entryType": "TimelineTimelineItem", "__typename": "TimelineTimelineItem", "itemContent": {"itemType": "TimelineUser", "__typename": "TimelineUser", "user_results": {"result": {"__typename": "User", "id": "VXNlcjo2NjY3MzkxNg==", "rest_id": "66673916", "affiliates_highlighted_label": {}, "has_graduated_access": true, "is_blue_verified": true, "profile_image_shape": "Circle", "legacy": {"can_dm": true, "can_media_tag": false, "created_at": "Tue Aug 18 12:58:38 +0000 2009", "default_profile": false, "default_profile_image": false, "description": "\ud83d\udcfb @TimesRadio \ud83d\uddf3\ufe0fHow To Win An Election https://t.co/CHuqLOmmM3\ud83d\udcd7Planes, Trains, Toilet Doors https://t.co/G2OZcmagHE \ud83d\udcf8https://t.co/7lr4CemRNA", "entities": {"description": {"urls": [{"display_url": "podfollow.com/how-to-win-an-\u2026", "expanded_url": "http://podfollow.com/how-to-win-an-election", "url": "https://t.co/CHuqLOmmM3", "indices": [39, 62]}, {"display_url": "amzn.eu/d/1G1hCjk", "expanded_url": "http://amzn.eu/d/1G1hCjk", "url": "https://t.co/G2OZcmagHE", "indices": [92, 115]}, {"display_url": "instagram.com/mattchorley", "expanded_url": "http://instagram.com/mattchorley", "url": "https://t.co/7lr4CemRNA", "indices": [117, 140]}]}, "url": {"urls": [{"display_url": "thetimes.co.uk/profile/matt-c\u2026", "expanded_url": "https://www.thetimes.co.uk/profile/matt-chorley", "url": "https://t.co/0Fje8oAcI2", "indices": [0, 23]}]}}, "fast_followers_count": 0, "favourites_count": 645, "followers_count": 115979, "friends_count": 2477, "has_custom_timelines": true, "is_translator": false, "listed_count": 1482, "location": "London", "media_count": 10363, "name": "Matt Chorley", "normal_followers_count": 115979, "pinned_tweet_ids_str": ["1724446441001623554"], "possibly_sensitive": false, "profile_banner_url": "https://pbs.twimg.com/profile_banners/66673916/1696447764", "profile_image_url_https": "https://pbs.twimg.com/profile_images/1709651902202347520/89LvjRBo_normal.jpg", "profile_interstitial_type": "", "screen_name": "MattChorley", "statuses_count": 94809, "translator_type": "none", "url": "https://t.co/0Fje8oAcI2", "verified": false, "want_retweets": false, "withheld_in_countries": []}, "professional": {"rest_id": "1470054145126281223", "professional_type": "Creator", "category": [{"id": 955, "name": "Journalist", "icon_name": "IconBriefcaseStroke"}]}}}, "userDisplayType": "User"}, "clientEventInfo": {"component": "FollowingSgs", "element": "user"}}}, {"entryId": "user-344613908", "sortIndex": "1725702210483911750", "content": {"entryType": "TimelineTimelineItem", "__typename": "TimelineTimelineItem", "itemContent": {"itemType": "TimelineUser", "__typename": "TimelineUser", "user_results": {"result": {"__typename": "User", "id": "VXNlcjozNDQ2MTM5MDg=", "rest_id": "344613908", "affiliates_highlighted_label": {}, "has_graduated_access": true, "is_blue_verified": false, "profile_image_shape": "Circle", "legacy": {"can_dm": false, "can_media_tag": false, "created_at": "Fri Jul 29 09:49:55 +0000 2011", "default_profile": false, "default_profile_image": false, "description": "Human rights news & analysis from @amnesty's global press office. Follow our media team: https://t.co/6v55NnSQZJ\u2026.", "entities": {"description": {"urls": [{"display_url": "twitter.com/amnestypress/l", "expanded_url": "https://twitter.com/amnestypress/l", "url": "https://t.co/6v55NnSQZJ", "indices": [89, 112]}]}, "url": {"urls": [{"display_url": "amnesty.org", "expanded_url": "http://www.amnesty.org", "url": "https://t.co/BD6TcblwyS", "indices": [0, 23]}]}}, "fast_followers_count": 0, "favourites_count": 11156, "followers_count": 52338, "friends_count": 8794, "has_custom_timelines": true, "is_translator": false, "listed_count": 839, "location": "press@amnesty.org ", "media_count": 2675, "name": "amnestypress", "normal_followers_count": 52338, "pinned_tweet_ids_str": [], "possibly_sensitive": false, "profile_banner_url": "https://pbs.twimg.com/profile_banners/344613908/1679050195", "profile_image_url_https": "https://pbs.twimg.com/profile_images/2602670382/a25ompeed749zwffrpkv_normal.jpeg", "profile_interstitial_type": "", "screen_name": "amnestypress", "statuses_count": 41426, "translator_type": "none", "url": "https://t.co/BD6TcblwyS", "verified": false, "want_retweets": false, "withheld_in_countries": []}}}, "userDisplayType": "User"}, "clientEventInfo": {"component": "FollowingSgs", "element": "user"}}}, {"entryId": "user-21687414", "sortIndex": "1725702210483911749", "content": {"entryType": "TimelineTimelineItem", "__typename": "TimelineTimelineItem", "itemContent": {"itemType": "TimelineUser", "__typename": "TimelineUser", "user_results": {"result": {"__typename": "User", "id": "VXNlcjoyMTY4NzQxNA==", "rest_id": "21687414", "affiliates_highlighted_label": {}, "has_graduated_access": true, "is_blue_verified": false, "profile_image_shape": "Circle", "legacy": {"can_dm": false, "can_media_tag": true, "created_at": "Mon Feb 23 20:06:17 +0000 2009", "default_profile": true, "default_profile_image": false, "description": "co-founder @charterworks ; formers: senior editor @theinformation, senior editor @nytopinion, co-founder @qz, managing editor, https://t.co/r8wrbQU8Gy", "entities": {"description": {"urls": [{"display_url": "WSJ.com", "expanded_url": "http://WSJ.com", "url": "https://t.co/r8wrbQU8Gy", "indices": [127, 150]}]}, "url": {"urls": [{"display_url": "charterworks.com/newsletter/", "expanded_url": "https://www.charterworks.com/newsletter/", "url": "https://t.co/nAR1bZljBc", "indices": [0, 23]}]}}, "fast_followers_count": 0, "favourites_count": 4127, "followers_count": 19302, "friends_count": 5811, "has_custom_timelines": false, "is_translator": false, "listed_count": 688, "location": "new york city", "media_count": 237, "name": "Kevin Delaney", "normal_followers_count": 19302, "pinned_tweet_ids_str": [], "possibly_sensitive": false, "profile_banner_url": "https://pbs.twimg.com/profile_banners/21687414/1600618655", "profile_image_url_https": "https://pbs.twimg.com/profile_images/2646875844/e4bc184cd920143889f09b7fa6eb4d63_normal.png", "profile_interstitial_type": "", "screen_name": "delaney", "statuses_count": 6250, "translator_type": "none", "url": "https://t.co/nAR1bZljBc", "verified": false, "want_retweets": false, "withheld_in_countries": []}}}, "userDisplayType": "User"}, "clientEventInfo": {"component": "FollowingSgs", "element": "user"}}}, {"entryId": "user-33820197", "sortIndex": "1725702210483911748", "content": {"entryType": "TimelineTimelineItem", "__typename": "TimelineTimelineItem", "itemContent": {"itemType": "TimelineUser", "__typename": "TimelineUser", "user_results": {"result": {"__typename": "User", "id": "VXNlcjozMzgyMDE5Nw==", "rest_id": "33820197", "affiliates_highlighted_label": {}, "has_graduated_access": true, "is_blue_verified": false, "profile_image_shape": "Circle", "legacy": {"can_dm": false, "can_media_tag": true, "created_at": "Tue Apr 21 05:08:45 +0000 2009", "default_profile": true, "default_profile_image": false, "description": "Director of News at the Asia Pacific Broadcasting Union (ABU). Formerly head of Asia Pacific news at the Australian Broadcasting Corporation.", "entities": {"description": {"urls": []}, "url": {"urls": [{"display_url": "abu.org.my", "expanded_url": "http://www.abu.org.my", "url": "https://t.co/JJOpOkRAiO", "indices": [0, 23]}]}}, "fast_followers_count": 0, "favourites_count": 839, "followers_count": 1659, "friends_count": 820, "has_custom_timelines": true, "is_translator": false, "listed_count": 71, "location": "Kuala Lumpur", "media_count": 601, "name": "Deborah Steele", "normal_followers_count": 1659, "pinned_tweet_ids_str": [], "possibly_sensitive": false, "profile_banner_url": "https://pbs.twimg.com/profile_banners/33820197/1500678857", "profile_image_url_https": "https://pbs.twimg.com/profile_images/1293735155677290498/YrHXx26U_normal.jpg", "profile_interstitial_type": "", "screen_name": "debsteele123", "statuses_count": 6760, "translator_type": "none", "url": "https://t.co/JJOpOkRAiO", "verified": false, "want_retweets": false, "withheld_in_countries": []}}}, "userDisplayType": "User"}, "clientEventInfo": {"component": "FollowingSgs", "element": "user"}}}, {"entryId": "user-115060258", "sortIndex": "1725702210483911747", "content": {"entryType": "TimelineTimelineItem", "__typename": "TimelineTimelineItem", "itemContent": {"itemType": "TimelineUser", "__typename": "TimelineUser", "user_results": {"result": {"__typename": "User", "id": "VXNlcjoxMTUwNjAyNTg=", "rest_id": "115060258", "affiliates_highlighted_label": {}, "has_graduated_access": true, "is_blue_verified": false, "profile_image_shape": "Circle", "legacy": {"protected": true, "can_dm": false, "can_media_tag": false, "created_at": "Wed Feb 17 13:50:37 +0000 2010", "default_profile": false, "default_profile_image": false, "description": "Former SBS journalist", "entities": {"description": {"urls": []}}, "fast_followers_count": 0, "favourites_count": 268, "followers_count": 1732, "friends_count": 1307, "has_custom_timelines": false, "is_translator": false, "listed_count": 50, "location": "Perth, WA", "media_count": 267, "name": "Ryan Emery", "normal_followers_count": 1732, "pinned_tweet_ids_str": [], "possibly_sensitive": false, "profile_banner_url": "https://pbs.twimg.com/profile_banners/115060258/1489733980", "profile_image_url_https": "https://pbs.twimg.com/profile_images/3711367445/efd4500cb726d55577a06ba9ead4b7cc_normal.jpeg", "profile_interstitial_type": "", "screen_name": "ryanremery", "statuses_count": 1783, "translator_type": "none", "verified": false, "want_retweets": false, "withheld_in_countries": []}}}, "userDisplayType": "User"}, "clientEventInfo": {"component": "FollowingSgs", "element": "user"}}}, {"entryId": "user-2292804986", "sortIndex": "1725702210483911746", "content": {"entryType": "TimelineTimelineItem", "__typename": "TimelineTimelineItem", "itemContent": {"itemType": "TimelineUser", "__typename": "TimelineUser", "user_results": {"result": {"__typename": "User", "id": "VXNlcjoyMjkyODA0OTg2", "rest_id": "2292804986", "affiliates_highlighted_label": {}, "has_graduated_access": true, "is_blue_verified": true, "profile_image_shape": "Circle", "legacy": {"can_dm": false, "can_media_tag": false, "created_at": "Wed Jan 15 14:42:45 +0000 2014", "default_profile": false, "default_profile_image": false, "description": "Founder of @stateofTLV. Podcast and Digital newsletter. All Israel. Was: \ud83c\udde8\ud83c\udde6 Ambassador to \ud83c\uddee\ud83c\uddf1. Lawyer. Torontonian. Am: Telavivian.", "entities": {"description": {"urls": []}, "url": {"urls": [{"display_url": "stateoftelaviv.com", "expanded_url": "http://stateoftelaviv.com", "url": "https://t.co/LBc5bKJXBe", "indices": [0, 23]}]}}, "fast_followers_count": 0, "favourites_count": 63547, "followers_count": 21143, "friends_count": 2352, "has_custom_timelines": true, "is_translator": false, "listed_count": 26, "location": "Tel Aviv", "media_count": 1050, "name": "Vivian Bercovici", "normal_followers_count": 21143, "pinned_tweet_ids_str": ["1173241637356691457"], "possibly_sensitive": false, "profile_banner_url": "https://pbs.twimg.com/profile_banners/2292804986/1455553515", "profile_image_url_https": "https://pbs.twimg.com/profile_images/569921815841996800/ZhLhieFg_normal.jpeg", "profile_interstitial_type": "", "screen_name": "VivianBercovici", "statuses_count": 37413, "translator_type": "none", "url": "https://t.co/LBc5bKJXBe", "verified": false, "want_retweets": false, "withheld_in_countries": []}, "professional": {"rest_id": "1471748702796718083", "professional_type": "Creator", "category": []}}}, "userDisplayType": "User"}, "clientEventInfo": {"component": "FollowingSgs", "element": "user"}}}, {"entryId": "user-81128019", "sortIndex": "1725702210483911745", "content": {"entryType": "TimelineTimelineItem", "__typename": "TimelineTimelineItem", "itemContent": {"itemType": "TimelineUser", "__typename": "TimelineUser", "user_results": {"result": {"__typename": "User", "id": "VXNlcjo4MTEyODAxOQ==", "rest_id": "81128019", "affiliates_highlighted_label": {}, "has_graduated_access": true, "is_blue_verified": false, "profile_image_shape": "Circle", "legacy": {"can_dm": false, "can_media_tag": true, "created_at": "Fri Oct 09 15:03:13 +0000 2009", "default_profile": true, "default_profile_image": false, "description": "Kerrywoman in exile. Presenter of @RTEUpfront and Upfront: The Podcast. Kerry Hospice Foundation patron. Views here my own.", "entities": {"description": {"urls": []}}, "fast_followers_count": 0, "favourites_count": 6670, "followers_count": 35680, "friends_count": 2442, "has_custom_timelines": true, "is_translator": false, "listed_count": 260, "location": "Dublin, Ireland", "media_count": 231, "name": "Katie Hannon", "normal_followers_count": 35680, "pinned_tweet_ids_str": [], "possibly_sensitive": false, "profile_banner_url": "https://pbs.twimg.com/profile_banners/81128019/1543706250", "profile_image_url_https": "https://pbs.twimg.com/profile_images/1309627975260872708/xK7eWjDh_normal.jpg", "profile_interstitial_type": "", "screen_name": "KatieGHannon", "statuses_count": 9641, "translator_type": "none", "verified": false, "want_retweets": false, "withheld_in_countries": []}}}, "userDisplayType": "User"}, "clientEventInfo": {"component": "FollowingSgs", "element": "user"}}}, {"entryId": "user-626317469", "sortIndex": "1725702210483911744", "content": {"entryType": "TimelineTimelineItem", "__typename": "TimelineTimelineItem", "itemContent": {"itemType": "TimelineUser", "__typename": "TimelineUser", "user_results": {"result": {"__typename": "User", "id": "VXNlcjo2MjYzMTc0Njk=", "rest_id": "626317469", "affiliates_highlighted_label": {}, "has_graduated_access": true, "is_blue_verified": false, "profile_image_shape": "Circle", "legacy": {"can_dm": true, "can_media_tag": true, "created_at": "Wed Jul 04 09:30:48 +0000 2012", "default_profile": false, "default_profile_image": false, "description": "Coach (Neuroleadership Inst, @OneofMany) - Editor - Journo. Storytelling+neuroscience. IG @leocorc Previous @IrishTimes Now @image_magazine \ud83d\udc15 \ud83c\uddee\ud83c\uddeain\ud83c\uddf5\ud83c\uddf9", "entities": {"description": {"urls": []}, "url": {"urls": [{"display_url": "thestorylab.rocks", "expanded_url": "http://www.thestorylab.rocks", "url": "https://t.co/yh6lnyKVRl", "indices": [0, 23]}]}}, "fast_followers_count": 0, "favourites_count": 5565, "followers_count": 1631, "friends_count": 1590, "has_custom_timelines": true, "is_translator": false, "listed_count": 57, "location": "Portugal via Ireland", "media_count": 909, "name": "Leonie Corcoran", "normal_followers_count": 1631, "pinned_tweet_ids_str": [], "possibly_sensitive": false, "profile_banner_url": "https://pbs.twimg.com/profile_banners/626317469/1461884159", "profile_image_url_https": "https://pbs.twimg.com/profile_images/1010067847966613505/FGGcdDDn_normal.jpg", "profile_interstitial_type": "", "screen_name": "LeonieCorcoran", "statuses_count": 7228, "translator_type": "none", "url": "https://t.co/yh6lnyKVRl", "verified": false, "want_retweets": false, "withheld_in_countries": []}}}, "userDisplayType": "User"}, "clientEventInfo": {"component": "FollowingSgs", "element": "user"}}}, {"entryId": "user-57841747", "sortIndex": "1725702210483911743", "content": {"entryType": "TimelineTimelineItem", "__typename": "TimelineTimelineItem", "itemContent": {"itemType": "TimelineUser", "__typename": "TimelineUser", "user_results": {"result": {"__typename": "User", "id": "VXNlcjo1Nzg0MTc0Nw==", "rest_id": "57841747", "affiliates_highlighted_label": {}, "has_graduated_access": true, "is_blue_verified": false, "profile_image_shape": "Circle", "legacy": {"can_dm": false, "can_media_tag": true, "created_at": "Sat Jul 18 03:26:46 +0000 2009", "default_profile": false, "default_profile_image": false, "description": "\u682a\u5f0f\u4f1a\u793e\u89d2\u5ddd\u30a2\u30b9\u30ad\u30fc\u7dcf\u5408\u7814\u7a76\u6240\u30fb\u6226\u7565\u63a8\u9032\u5ba4\u3002\u30a8\u30ea\u30a2LOVE\u30a6\u30a9\u30fc\u30ab\u30fc\u7dcf\u7de8\u96c6\u9577\u3002\u56fd\u969b\u5927\u5b66GLOCOM\u5ba2\u54e1\u7814\u7a76\u54e1\u3002\u4e00\u822c\u793e\u56e3\u6cd5\u4eba\u30e1\u30bf\u89b3\u5149\u63a8\u9032\u6a5f\u69cb\u7406\u4e8b\u3002\u4eac\u90fd\u5e02\u57cb\u8535\u6587\u5316\u8ca1\u7814\u7a76\u6240\u7406\u4e8b\u3002\u5927\u962a\u5e9c\u65e5\u672c\u4e07\u56fd\u535a\u89a7\u4f1a\u8a18\u5ff5\u516c\u5712\u904b\u55b6\u5be9\u8b70\u4f1a\u4f1a\u9577\u4ee3\u884c\u3002\u7523\u7d4c\u65b0\u805e\u301c\u798f\u6b66\u66f8\u5e97\u301c\u89d2\u5ddd4\u8a8c\u7de8\u96c6\u9577", "entities": {"description": {"urls": []}, "url": {"urls": [{"display_url": "ascii.jp", "expanded_url": "https://ascii.jp/", "url": "https://t.co/vOXgGH78Wg", "indices": [0, 23]}]}}, "fast_followers_count": 0, "favourites_count": 412025, "followers_count": 17797, "friends_count": 19534, "has_custom_timelines": true, "is_translator": false, "listed_count": 849, "location": "\u6771\u4eac\u90fd\u5343\u4ee3\u7530\u533a\u4e94\u756a\u753a3-1", "media_count": 44522, "name": "\u7389\u7f6e\u6cf0\u7d00\u3000\u30a8\u30ea\u30a2LOVE Walker\u7dcf\u7de8\u96c6\u9577", "normal_followers_count": 17797, "pinned_tweet_ids_str": ["877744447701753856"], "possibly_sensitive": false, "profile_banner_url": "https://pbs.twimg.com/profile_banners/57841747/1388811429", "profile_image_url_https": "https://pbs.twimg.com/profile_images/1610437014905843712/4VvUE20n_normal.jpg", "profile_interstitial_type": "", "screen_name": "tamatama2", "statuses_count": 907659, "translator_type": "none", "url": "https://t.co/vOXgGH78Wg", "verified": false, "want_retweets": false, "withheld_in_countries": []}, "professional": {"rest_id": "1455851930983354370", "professional_type": "Creator", "category": [{"id": 580, "name": "Media & News Company", "icon_name": "IconBriefcaseStroke"}]}}}, "userDisplayType": "User"}, "clientEventInfo": {"component": "FollowingSgs", "element": "user"}}}, {"entryId": "user-8953122", "sortIndex": "1725702210483911742", "content": {"entryType": "TimelineTimelineItem", "__typename": "TimelineTimelineItem", "itemContent": {"itemType": "TimelineUser", "__typename": "TimelineUser", "user_results": {"result": {"__typename": "User", "id": "VXNlcjo4OTUzMTIy", "rest_id": "8953122", "affiliates_highlighted_label": {}, "has_graduated_access": true, "is_blue_verified": false, "profile_image_shape": "Circle", "legacy": {"can_dm": false, "can_media_tag": false, "created_at": "Tue Sep 18 15:08:32 +0000 2007", "default_profile": false, "default_profile_image": false, "description": "Home of the Truth-O-Meter and independent fact-checking. Part of @Poynter. Sign up for our newsletter: https://t.co/9ygUqAw2P8", "entities": {"description": {"urls": [{"display_url": "politifact.com/signup", "expanded_url": "http://politifact.com/signup", "url": "https://t.co/9ygUqAw2P8", "indices": [103, 126]}]}, "url": {"urls": [{"display_url": "politifact.com", "expanded_url": "http://www.politifact.com", "url": "https://t.co/xv5z0ieh6l", "indices": [0, 23]}]}}, "fast_followers_count": 0, "favourites_count": 4527, "followers_count": 643728, "friends_count": 7659, "has_custom_timelines": true, "is_translator": false, "listed_count": 10533, "location": "Washington, DC", "media_count": 25022, "name": "PolitiFact", "normal_followers_count": 643728, "pinned_tweet_ids_str": ["1650897224086306821"], "possibly_sensitive": false, "profile_banner_url": "https://pbs.twimg.com/profile_banners/8953122/1637181989", "profile_image_url_https": "https://pbs.twimg.com/profile_images/1286766140115517441/8rq6ZxZm_normal.jpg", "profile_interstitial_type": "", "screen_name": "PolitiFact", "statuses_count": 67108, "translator_type": "none", "url": "https://t.co/xv5z0ieh6l", "verified": false, "want_retweets": false, "withheld_in_countries": []}, "professional": {"rest_id": "1488963816356560896", "professional_type": "Business", "category": [{"id": 580, "name": "Media & News Company", "icon_name": "IconBriefcaseStroke"}]}}}, "userDisplayType": "User"}, "clientEventInfo": {"component": "FollowingSgs", "element": "user"}}}, {"entryId": "user-205622130", "sortIndex": "1725702210483911741", "content": {"entryType": "TimelineTimelineItem", "__typename": "TimelineTimelineItem", "itemContent": {"itemType": "TimelineUser", "__typename": "TimelineUser", "user_results": {"result": {"__typename": "User", "id": "VXNlcjoyMDU2MjIxMzA=", "rest_id": "205622130", "affiliates_highlighted_label": {}, "has_graduated_access": true, "is_blue_verified": true, "profile_image_shape": "Circle", "legacy": {"can_dm": false, "can_media_tag": true, "created_at": "Thu Oct 21 08:06:17 +0000 2010", "default_profile": false, "default_profile_image": false, "description": "Official Kremlin news\nOfficial Telegram channel: https://t.co/ASrzdwRxSU", "entities": {"description": {"urls": [{"display_url": "t.me/news_kremlin_e\u2026", "expanded_url": "https://t.me/news_kremlin_eng", "url": "https://t.co/ASrzdwRxSU", "indices": [49, 72]}]}, "url": {"urls": [{"display_url": "en.kremlin.ru", "expanded_url": "http://en.kremlin.ru/", "url": "https://t.co/MfmVE6eQBU", "indices": [0, 23]}]}}, "fast_followers_count": 0, "favourites_count": 1, "followers_count": 1852856, "friends_count": 22, "has_custom_timelines": false, "is_translator": false, "listed_count": 7980, "location": "Moscow, Russian Federation", "media_count": 3201, "name": "President of Russia", "normal_followers_count": 1852856, "pinned_tweet_ids_str": [], "possibly_sensitive": false, "profile_banner_url": "https://pbs.twimg.com/profile_banners/205622130/1402044538", "profile_image_url_https": "https://pbs.twimg.com/profile_images/501717583846842368/psd9aFLl_normal.png", "profile_interstitial_type": "", "screen_name": "KremlinRussia_E", "statuses_count": 9239, "translator_type": "none", "url": "https://t.co/MfmVE6eQBU", "verified": false, "verified_type": "Government", "want_retweets": false, "withheld_in_countries": []}}}, "userDisplayType": "User"}, "clientEventInfo": {"component": "FollowingSgs", "element": "user"}}}, {"entryId": "user-1390655238", "sortIndex": "1725702210483911740", "content": {"entryType": "TimelineTimelineItem", "__typename": "TimelineTimelineItem", "itemContent": {"itemType": "TimelineUser", "__typename": "TimelineUser", "user_results": {"result": {"__typename": "User", "id": "VXNlcjoxMzkwNjU1MjM4", "rest_id": "1390655238", "affiliates_highlighted_label": {}, "has_graduated_access": true, "is_blue_verified": false, "profile_image_shape": "Circle", "legacy": {"can_dm": false, "can_media_tag": true, "created_at": "Mon Apr 29 23:12:49 +0000 2013", "default_profile": false, "default_profile_image": false, "description": "\ud83c\udde6\ud83c\uddfa This is the official account of Australia's High Commissioner to New Zealand. For consular assistance in NZ phone +6444736411", "entities": {"description": {"urls": []}, "url": {"urls": [{"display_url": "newzealand.embassy.gov.au", "expanded_url": "http://www.newzealand.embassy.gov.au", "url": "https://t.co/OknzEjiYt3", "indices": [0, 23]}]}}, "fast_followers_count": 0, "favourites_count": 2772, "followers_count": 4550, "friends_count": 686, "has_custom_timelines": false, "is_translator": false, "listed_count": 80, "location": "Wellington", "media_count": 1128, "name": "Harinder Sidhu", "normal_followers_count": 4550, "pinned_tweet_ids_str": [], "possibly_sensitive": false, "profile_banner_url": "https://pbs.twimg.com/profile_banners/1390655238/1697420059", "profile_image_url_https": "https://pbs.twimg.com/profile_images/1510786600607035396/yuB-_S5y_normal.jpg", "profile_interstitial_type": "", "screen_name": "AusHCNZ", "statuses_count": 3842, "translator_type": "none", "url": "https://t.co/OknzEjiYt3", "verified": false, "want_retweets": false, "withheld_in_countries": []}}}, "userDisplayType": "User"}, "clientEventInfo": {"component": "FollowingSgs", "element": "user"}}}, {"entryId": "user-35925814", "sortIndex": "1725702210483911739", "content": {"entryType": "TimelineTimelineItem", "__typename": "TimelineTimelineItem", "itemContent": {"itemType": "TimelineUser", "__typename": "TimelineUser", "user_results": {"result": {"__typename": "User", "id": "VXNlcjozNTkyNTgxNA==", "rest_id": "35925814", "affiliates_highlighted_label": {}, "has_graduated_access": true, "is_blue_verified": false, "profile_image_shape": "Circle", "legacy": {"can_dm": false, "can_media_tag": true, "created_at": "Tue Apr 28 00:38:19 +0000 2009", "default_profile": false, "default_profile_image": false, "description": "", "entities": {"description": {"urls": []}}, "fast_followers_count": 0, "favourites_count": 950, "followers_count": 38371, "friends_count": 805, "has_custom_timelines": false, "is_translator": false, "listed_count": 136, "location": "", "media_count": 46, "name": "Zach Nelson", "normal_followers_count": 38371, "pinned_tweet_ids_str": [], "possibly_sensitive": false, "profile_banner_url": "https://pbs.twimg.com/profile_banners/35925814/1372210062", "profile_image_url_https": "https://pbs.twimg.com/profile_images/1311292858322821121/fldnH0es_normal.jpg", "profile_interstitial_type": "", "screen_name": "ZachNelson", "statuses_count": 655, "translator_type": "none", "verified": false, "want_retweets": false, "withheld_in_countries": []}}}, "userDisplayType": "User"}, "clientEventInfo": {"component": "FollowingSgs", "element": "user"}}}, {"entryId": "user-250765341", "sortIndex": "1725702210483911738", "content": {"entryType": "TimelineTimelineItem", "__typename": "TimelineTimelineItem", "itemContent": {"itemType": "TimelineUser", "__typename": "TimelineUser", "user_results": {"result": {"__typename": "User", "id": "VXNlcjoyNTA3NjUzNDE=", "rest_id": "250765341", "affiliates_highlighted_label": {}, "has_graduated_access": true, "is_blue_verified": false, "profile_image_shape": "Circle", "legacy": {"can_dm": false, "can_media_tag": true, "created_at": "Fri Feb 11 19:19:26 +0000 2011", "default_profile": false, "default_profile_image": false, "description": "Lead executive communications at The New York Times. Other tweets on occasion. Usually about dogs, especially labs.", "entities": {"description": {"urls": []}, "url": {"urls": [{"display_url": "nytimes.com", "expanded_url": "http://nytimes.com", "url": "https://t.co/NNCB0pO3YH", "indices": [0, 23]}]}}, "fast_followers_count": 0, "favourites_count": 2837, "followers_count": 3774, "friends_count": 867, "has_custom_timelines": true, "is_translator": false, "listed_count": 83, "location": "NYC ", "media_count": 73, "name": "Eileen Murphy", "normal_followers_count": 3774, "pinned_tweet_ids_str": [], "possibly_sensitive": false, "profile_banner_url": "https://pbs.twimg.com/profile_banners/250765341/1630022977", "profile_image_url_https": "https://pbs.twimg.com/profile_images/699627181203398657/amgb30Hl_normal.jpg", "profile_interstitial_type": "", "screen_name": "NYTeileen", "statuses_count": 4265, "translator_type": "none", "url": "https://t.co/NNCB0pO3YH", "verified": false, "want_retweets": false, "withheld_in_countries": []}}}, "userDisplayType": "User"}, "clientEventInfo": {"component": "FollowingSgs", "element": "user"}}}, {"entryId": "user-289200738", "sortIndex": "1725702210483911737", "content": {"entryType": "TimelineTimelineItem", "__typename": "TimelineTimelineItem", "itemContent": {"itemType": "TimelineUser", "__typename": "TimelineUser", "user_results": {"result": {"__typename": "User", "id": "VXNlcjoyODkyMDA3Mzg=", "rest_id": "289200738", "affiliates_highlighted_label": {}, "has_graduated_access": true, "is_blue_verified": false, "profile_image_shape": "Circle", "legacy": {"can_dm": false, "can_media_tag": true, "created_at": "Thu Apr 28 06:17:30 +0000 2011", "default_profile": false, "default_profile_image": false, "description": "Senior Writer for Bloomberg News. Author of Goddess of Battle. Views expressed in Twitter feed are my own.", "entities": {"description": {"urls": []}, "url": {"urls": [{"display_url": "bloomberg.com", "expanded_url": "http://www.bloomberg.com", "url": "https://t.co/XS59IcFF5g", "indices": [0, 23]}]}}, "fast_followers_count": 0, "favourites_count": 48, "followers_count": 1785, "friends_count": 654, "has_custom_timelines": false, "is_translator": false, "listed_count": 62, "location": "Israel, West Bank, Gaza", "media_count": 2, "name": "Gwen Ackerman", "normal_followers_count": 1785, "pinned_tweet_ids_str": [], "possibly_sensitive": false, "profile_image_url_https": "https://pbs.twimg.com/profile_images/1627787086412521472/YSZm7kBE_normal.jpg", "profile_interstitial_type": "", "screen_name": "GwenSahar", "statuses_count": 779, "translator_type": "none", "url": "https://t.co/XS59IcFF5g", "verified": false, "want_retweets": false, "withheld_in_countries": []}}}, "userDisplayType": "User"}, "clientEventInfo": {"component": "FollowingSgs", "element": "user"}}}, {"entryId": "user-901270711", "sortIndex": "1725702210483911736", "content": {"entryType": "TimelineTimelineItem", "__typename": "TimelineTimelineItem", "itemContent": {"itemType": "TimelineUser", "__typename": "TimelineUser", "user_results": {"result": {"__typename": "User", "id": "VXNlcjo5MDEyNzA3MTE=", "rest_id": "901270711", "affiliates_highlighted_label": {}, "has_graduated_access": true, "is_blue_verified": false, "profile_image_shape": "Circle", "legacy": {"can_dm": false, "can_media_tag": true, "created_at": "Wed Oct 24 05:57:39 +0000 2012", "default_profile": false, "default_profile_image": false, "description": "\u30b8\u30e3\u30fc\u30ca\u30ea\u30b9\u30c8\u3002\u5143\u5927\u5b66\u6559\u54e1\u3002\u653f\u7b56\u3084\u30e1\u30c7\u30a3\u30a2\u306a\u3069\u30c1\u30a7\u30c3\u30af\u3002\u82e5\u8005\u5fdc\u63f4\u3002RT.\u30ea\u30f3\u30af\u306f\u3001\u6ce8\u76ee\u3092\u3068\u3044\u3046\u610f\u5473\u3002\u500b\u4eba\u30d6\u30ed\u30b0\u300c\u30cb\u30e5\u30fc\u30b9\u30c1\u30a7\u30c3\u30ab\u30fc\u3000News Checker\u300d", "entities": {"description": {"urls": []}, "url": {"urls": [{"display_url": "economicjounalism.blog.fc2.com", "expanded_url": "http://economicjounalism.blog.fc2.com/", "url": "https://t.co/jhn6tKp3U4", "indices": [0, 23]}]}}, "fast_followers_count": 0, "favourites_count": 2791, "followers_count": 1554, "friends_count": 635, "has_custom_timelines": true, "is_translator": false, "listed_count": 50, "location": "\u65e5\u672c \u6771\u4eac", "media_count": 291, "name": "\u5c0f\u6b64\u6728\u6f54\u3000OKONOGI Kiyoshi", "normal_followers_count": 1554, "pinned_tweet_ids_str": [], "possibly_sensitive": false, "profile_banner_url": "https://pbs.twimg.com/profile_banners/901270711/1451190777", "profile_image_url_https": "https://pbs.twimg.com/profile_images/1181137584908431360/PkHoNtmM_normal.jpg", "profile_interstitial_type": "", "screen_name": "okonogie", "statuses_count": 13325, "translator_type": "none", "url": "https://t.co/jhn6tKp3U4", "verified": false, "want_retweets": false, "withheld_in_countries": []}, "professional": {"rest_id": "1543584980085121024", "professional_type": "Business", "category": [{"id": 955, "name": "Journalist", "icon_name": "IconBriefcaseStroke"}]}}}, "userDisplayType": "User"}, "clientEventInfo": {"component": "FollowingSgs", "element": "user"}}}, {"entryId": "user-3069261371", "sortIndex": "1725702210483911735", "content": {"entryType": "TimelineTimelineItem", "__typename": "TimelineTimelineItem", "itemContent": {"itemType": "TimelineUser", "__typename": "TimelineUser", "user_results": {"result": {"__typename": "User", "id": "VXNlcjozMDY5MjYxMzcx", "rest_id": "3069261371", "affiliates_highlighted_label": {}, "has_graduated_access": true, "is_blue_verified": false, "profile_image_shape": "Square", "legacy": {"can_dm": true, "can_media_tag": true, "created_at": "Wed Mar 04 05:12:57 +0000 2015", "default_profile": false, "default_profile_image": false, "description": "We represent the European Union in Australia at all levels. We work with #EU Member State missions in #CBR. Follow our Ambassador @GVisentinEU", "entities": {"description": {"urls": []}, "url": {"urls": [{"display_url": "eeas.europa.eu/australia", "expanded_url": "http://eeas.europa.eu/australia", "url": "https://t.co/g2kUgWt4lm", "indices": [0, 23]}]}}, "fast_followers_count": 0, "favourites_count": 45627, "followers_count": 7916, "friends_count": 6205, "has_custom_timelines": true, "is_translator": false, "listed_count": 370, "location": "Canberra, Australia", "media_count": 2138, "name": "EU in Australia", "normal_followers_count": 7916, "pinned_tweet_ids_str": ["1722782007539720257"], "possibly_sensitive": false, "profile_banner_url": "https://pbs.twimg.com/profile_banners/3069261371/1646795164", "profile_image_url_https": "https://pbs.twimg.com/profile_images/1542657288455987201/e76AGGCX_normal.jpg", "profile_interstitial_type": "", "screen_name": "EUinAus", "statuses_count": 24673, "translator_type": "none", "url": "https://t.co/g2kUgWt4lm", "verified": false, "verified_type": "Government", "want_retweets": false, "withheld_in_countries": []}}}, "userDisplayType": "User"}, "clientEventInfo": {"component": "FollowingSgs", "element": "user"}}}, {"entryId": "user-151106990", "sortIndex": "1725702210483911734", "content": {"entryType": "TimelineTimelineItem", "__typename": "TimelineTimelineItem", "itemContent": {"itemType": "TimelineUser", "__typename": "TimelineUser", "user_results": {"result": {"__typename": "User", "id": "VXNlcjoxNTExMDY5OTA=", "rest_id": "151106990", "affiliates_highlighted_label": {}, "has_graduated_access": true, "is_blue_verified": true, "profile_image_shape": "Circle", "legacy": {"can_dm": true, "can_media_tag": true, "created_at": "Wed Jun 02 16:28:27 +0000 2010", "default_profile": false, "default_profile_image": false, "description": "Independent research and analysis on the most important policy issues in the world. Sign up for the daily Brookings Brief: https://t.co/nZdfZxn4JQ", "entities": {"description": {"urls": [{"display_url": "brook.gs/3JuZxRE", "expanded_url": "http://brook.gs/3JuZxRE", "url": "https://t.co/nZdfZxn4JQ", "indices": [123, 146]}]}, "url": {"urls": [{"display_url": "brookings.edu", "expanded_url": "http://www.brookings.edu", "url": "https://t.co/ep6cP2bAlU", "indices": [0, 23]}]}}, "fast_followers_count": 0, "favourites_count": 3729, "followers_count": 449365, "friends_count": 4423, "has_custom_timelines": true, "is_translator": false, "listed_count": 7837, "location": "Washington, DC", "media_count": 29816, "name": "The Brookings Institution", "normal_followers_count": 449365, "pinned_tweet_ids_str": ["1674119113868992512"], "possibly_sensitive": false, "profile_banner_url": "https://pbs.twimg.com/profile_banners/151106990/1687888812", "profile_image_url_https": "https://pbs.twimg.com/profile_images/1673753102153916416/m0qIz2OT_normal.jpg", "profile_interstitial_type": "", "screen_name": "BrookingsInst", "statuses_count": 110562, "translator_type": "none", "url": "https://t.co/ep6cP2bAlU", "verified": false, "want_retweets": false, "withheld_in_countries": []}, "professional": {"rest_id": "1511052104307286019", "professional_type": "Business", "category": [{"id": 688, "name": "Non-Governmental & Nonprofit Organization ", "icon_name": "IconBriefcaseStroke"}]}}}, "userDisplayType": "User"}, "clientEventInfo": {"component": "FollowingSgs", "element": "user"}}}, {"entryId": "user-76354665", "sortIndex": "1725702210483911733", "content": {"entryType": "TimelineTimelineItem", "__typename": "TimelineTimelineItem", "itemContent": {"itemType": "TimelineUser", "__typename": "TimelineUser", "user_results": {"result": {"__typename": "User", "id": "VXNlcjo3NjM1NDY2NQ==", "rest_id": "76354665", "affiliates_highlighted_label": {}, "has_graduated_access": true, "is_blue_verified": false, "profile_image_shape": "Circle", "legacy": {"can_dm": false, "can_media_tag": false, "created_at": "Tue Sep 22 15:03:06 +0000 2009", "default_profile": false, "default_profile_image": false, "description": "elation - elegance - exaltation", "entities": {"description": {"urls": []}, "url": {"urls": [{"display_url": "hirotami.jp", "expanded_url": "http://hirotami.jp", "url": "https://t.co/p63gYGlvwc", "indices": [0, 23]}]}}, "fast_followers_count": 0, "favourites_count": 1011, "followers_count": 7948, "friends_count": 272, "has_custom_timelines": false, "is_translator": false, "listed_count": 889, "location": "", "media_count": 335, "name": "Hirotami Murakoshi", "normal_followers_count": 7948, "pinned_tweet_ids_str": [], "possibly_sensitive": false, "profile_image_url_https": "https://pbs.twimg.com/profile_images/1615366330810785792/z7HerLo__normal.jpg", "profile_interstitial_type": "", "screen_name": "hirotami_m", "statuses_count": 7059, "translator_type": "none", "url": "https://t.co/p63gYGlvwc", "verified": false, "want_retweets": false, "withheld_in_countries": []}, "professional": {"rest_id": "1493836002208542723", "professional_type": "Creator", "category": []}}}, "userDisplayType": "User"}, "clientEventInfo": {"component": "FollowingSgs", "element": "user"}}}, {"entryId": "user-131574396", "sortIndex": "1725702210483911732", "content": {"entryType": "TimelineTimelineItem", "__typename": "TimelineTimelineItem", "itemContent": {"itemType": "TimelineUser", "__typename": "TimelineUser", "user_results": {"result": {"__typename": "User", "id": "VXNlcjoxMzE1NzQzOTY=", "rest_id": "131574396", "affiliates_highlighted_label": {}, "has_graduated_access": true, "is_blue_verified": true, "profile_image_shape": "Circle", "legacy": {"can_dm": false, "can_media_tag": false, "created_at": "Sat Apr 10 17:46:14 +0000 2010", "default_profile": false, "default_profile_image": false, "description": "Primeira presidenta do Brasil (2011-2016)   Presidenta do Novo Banco de Desenvolvimento (NDB)", "entities": {"description": {"urls": []}, "url": {"urls": [{"display_url": "dilma.com.br", "expanded_url": "http://dilma.com.br", "url": "https://t.co/X2EFbAyVFw", "indices": [0, 23]}]}}, "fast_followers_count": 0, "favourites_count": 661, "followers_count": 6656584, "friends_count": 287, "has_custom_timelines": true, "is_translator": false, "listed_count": 15309, "location": "Brazil", "media_count": 1209, "name": "Dilma Rousseff", "normal_followers_count": 6656584, "pinned_tweet_ids_str": [], "possibly_sensitive": false, "profile_banner_url": "https://pbs.twimg.com/profile_banners/131574396/1681398705", "profile_image_url_https": "https://pbs.twimg.com/profile_images/1646531411921313793/l0_ZqUkW_normal.jpg", "profile_interstitial_type": "", "screen_name": "dilmabr", "statuses_count": 9195, "translator_type": "regular", "url": "https://t.co/X2EFbAyVFw", "verified": false, "want_retweets": false, "withheld_in_countries": []}}}, "userDisplayType": "User"}, "clientEventInfo": {"component": "FollowingSgs", "element": "user"}}}, {"entryId": "user-3059362106", "sortIndex": "1725702210483911731", "content": {"entryType": "TimelineTimelineItem", "__typename": "TimelineTimelineItem", "itemContent": {"itemType": "TimelineUser", "__typename": "TimelineUser", "user_results": {"result": {"__typename": "User", "id": "VXNlcjozMDU5MzYyMTA2", "rest_id": "3059362106", "affiliates_highlighted_label": {}, "has_graduated_access": true, "is_blue_verified": false, "profile_image_shape": "Circle", "legacy": {"can_dm": false, "can_media_tag": true, "created_at": "Tue Mar 03 06:52:02 +0000 2015", "default_profile": false, "default_profile_image": false, "description": "UK Research and Innovation China helps UKRI facilitate excellent, impactful UK-China partnerships that address global challenges.", "entities": {"description": {"urls": []}, "url": {"urls": [{"display_url": "ukri.org/research/inter\u2026", "expanded_url": "https://www.ukri.org/research/international/ukri-international-offices/ukri-china/", "url": "https://t.co/G5RCq6AX5l", "indices": [0, 23]}]}}, "fast_followers_count": 0, "favourites_count": 425, "followers_count": 2028, "friends_count": 405, "has_custom_timelines": false, "is_translator": false, "listed_count": 50, "location": "British Embassy Beijing", "media_count": 557, "name": "UKRI China", "normal_followers_count": 2028, "pinned_tweet_ids_str": ["1197753558004690944"], "possibly_sensitive": false, "profile_banner_url": "https://pbs.twimg.com/profile_banners/3059362106/1663746900", "profile_image_url_https": "https://pbs.twimg.com/profile_images/1676477371958935552/YuSEpAnh_normal.jpg", "profile_interstitial_type": "", "screen_name": "UKRI_China", "statuses_count": 1653, "translator_type": "none", "url": "https://t.co/G5RCq6AX5l", "verified": false, "want_retweets": false, "withheld_in_countries": []}}}, "userDisplayType": "User"}, "clientEventInfo": {"component": "FollowingSgs", "element": "user"}}}, {"entryId": "user-240968515", "sortIndex": "1725702210483911730", "content": {"entryType": "TimelineTimelineItem", "__typename": "TimelineTimelineItem", "itemContent": {"itemType": "TimelineUser", "__typename": "TimelineUser", "user_results": {"result": {"__typename": "User", "id": "VXNlcjoyNDA5Njg1MTU=", "rest_id": "240968515", "affiliates_highlighted_label": {}, "has_graduated_access": true, "is_blue_verified": false, "profile_image_shape": "Circle", "legacy": {"can_dm": false, "can_media_tag": true, "created_at": "Fri Jan 21 04:16:40 +0000 2011", "default_profile": true, "default_profile_image": false, "description": "#adelaide #saparli #auspol #PAFC #AOC South Australia. Daddy.", "entities": {"description": {"urls": []}}, "fast_followers_count": 0, "favourites_count": 27823, "followers_count": 6896, "friends_count": 6503, "has_custom_timelines": true, "is_translator": false, "listed_count": 140, "location": "Kaurna land", "media_count": 2964, "name": "Miles Kemp", "normal_followers_count": 6896, "pinned_tweet_ids_str": ["1712652042534355327"], "possibly_sensitive": false, "profile_image_url_https": "https://pbs.twimg.com/profile_images/1338697818509217792/6kVXoUCf_normal.jpg", "profile_interstitial_type": "", "screen_name": "bykemp", "statuses_count": 34604, "translator_type": "none", "verified": false, "want_retweets": false, "withheld_in_countries": []}}}, "userDisplayType": "User"}, "clientEventInfo": {"component": "FollowingSgs", "element": "user"}}}, {"entryId": "user-820939680", "sortIndex": "1725702210483911729", "content": {"entryType": "TimelineTimelineItem", "__typename": "TimelineTimelineItem", "itemContent": {"itemType": "TimelineUser", "__typename": "TimelineUser", "user_results": {"result": {"__typename": "User", "id": "VXNlcjo4MjA5Mzk2ODA=", "rest_id": "820939680", "affiliates_highlighted_label": {}, "has_graduated_access": true, "is_blue_verified": false, "profile_image_shape": "Circle", "legacy": {"can_dm": false, "can_media_tag": false, "created_at": "Thu Sep 13 05:36:32 +0000 2012", "default_profile": true, "default_profile_image": false, "description": "Senior Staff Writer, the Asahi Shimbun. Former London Bureau Chief. \u671d\u65e5\u65b0\u805e\u7de8\u96c6\u59d4\u54e1\u3002\u5143\u30e8\u30fc\u30ed\u30c3\u30d1\u7dcf\u5c40\u9577\u3002\u56fd\u969b\u95a2\u4fc2\u3001SDG\uff53\u3001\u30af\u30e9\u30b7\u30c3\u30af\u97f3\u697d\u3082\u3002\u8457\u66f8\u300c\u97ff\u304d\u3092\u307f\u304c\u304f\u3000\u97f3\u97ff\u8a2d\u8a08\u5bb6\u8c4a\u7530\u6cf0\u4e45\u306e\u4ed5\u4e8b\u300d\u3002\u6295\u7a3f\u306f\u4f1a\u793e\u306e\u898b\u89e3\u3067\u306f\u306a\u304f\uff32\uff34\u3084\u30ea\u30f3\u30af\u306f\u8cdb\u610f\u3068\u306f\u9650\u308a\u307e\u305b\u3093\u3002", "entities": {"description": {"urls": []}, "url": {"urls": [{"display_url": "sitesearch.asahi.com/.cgi/sitesearc\u2026", "expanded_url": "https://sitesearch.asahi.com/.cgi/sitesearch/sitesearch.pl?Keywords=%E7%9F%B3%E5%90%88%E5%8A%9B&Sear", "url": "https://t.co/IhZ2Cs8U3G", "indices": [0, 23]}]}}, "fast_followers_count": 0, "favourites_count": 278, "followers_count": 3580, "friends_count": 3621, "has_custom_timelines": false, "is_translator": false, "listed_count": 181, "location": "Osaka, Japan", "media_count": 127, "name": "\u77f3\u5408\u529b\u3000Tsutomu\u3000ISHIAI", "normal_followers_count": 3580, "pinned_tweet_ids_str": [], "possibly_sensitive": false, "profile_banner_url": "https://pbs.twimg.com/profile_banners/820939680/1615377568", "profile_image_url_https": "https://pbs.twimg.com/profile_images/1369619177229713416/rCN-EmH6_normal.jpg", "profile_interstitial_type": "", "screen_name": "TsutomuISHIAI", "statuses_count": 2947, "translator_type": "none", "url": "https://t.co/IhZ2Cs8U3G", "verified": false, "want_retweets": false, "withheld_in_countries": []}}}, "userDisplayType": "User"}, "clientEventInfo": {"component": "FollowingSgs", "element": "user"}}}, {"entryId": "user-38722560", "sortIndex": "1725702210483911728", "content": {"entryType": "TimelineTimelineItem", "__typename": "TimelineTimelineItem", "itemContent": {"itemType": "TimelineUser", "__typename": "TimelineUser", "user_results": {"result": {"__typename": "User", "id": "VXNlcjozODcyMjU2MA==", "rest_id": "38722560", "affiliates_highlighted_label": {}, "has_graduated_access": true, "is_blue_verified": false, "profile_image_shape": "Circle", "legacy": {"can_dm": false, "can_media_tag": true, "created_at": "Fri May 08 19:05:21 +0000 2009", "default_profile": false, "default_profile_image": false, "description": "Former Editor-in-chief, The Chronicle Herald,  Atlantic Canada daily. Retired, 2018.", "entities": {"description": {"urls": []}}, "fast_followers_count": 0, "favourites_count": 98, "followers_count": 1091, "friends_count": 713, "has_custom_timelines": false, "is_translator": false, "listed_count": 61, "location": "Halifax, Nova Scotia, Canada", "media_count": 267, "name": "Bob Howse", "normal_followers_count": 1091, "pinned_tweet_ids_str": [], "possibly_sensitive": false, "profile_banner_url": "https://pbs.twimg.com/profile_banners/38722560/1395607537", "profile_image_url_https": "https://pbs.twimg.com/profile_images/206813105/howseherald3_normal.jpg", "profile_interstitial_type": "", "screen_name": "CH_BobHowse", "statuses_count": 2733, "translator_type": "none", "verified": false, "want_retweets": false, "withheld_in_countries": []}}}, "userDisplayType": "User"}, "clientEventInfo": {"component": "FollowingSgs", "element": "user"}}}, {"entryId": "user-1515867654", "sortIndex": "1725702210483911727", "content": {"entryType": "TimelineTimelineItem", "__typename": "TimelineTimelineItem", "itemContent": {"itemType": "TimelineUser", "__typename": "TimelineUser", "user_results": {"result": {"__typename": "User", "id": "VXNlcjoxNTE1ODY3NjU0", "rest_id": "1515867654", "affiliates_highlighted_label": {}, "has_graduated_access": true, "is_blue_verified": false, "profile_image_shape": "Circle", "legacy": {"can_dm": false, "can_media_tag": true, "created_at": "Fri Jun 14 09:26:19 +0000 2013", "default_profile": false, "default_profile_image": false, "description": "\u9999\u6e2f\u306b\u4f4f\u3093\u3067\u3044\u305f\u6642\u671f\u3001\u4e2d\u56fd\u8a9e\u306e\u52c9\u5f37\u306b\u52b1\u307f\u307e\u3057\u305f\u304c\u3001\u666e\u901a\u8a71\u3068\u5e83\u6771\u8a9e\u304c\u30b4\u30c1\u30e3\u30b4\u30c1\u30e3\u306b\u306a\u3063\u3066\u3001\u601d\u3063\u3066\u3044\u305f\u307b\u3069\u306f\u4e0a\u9054\u3057\u307e\u305b\u3093\u3067\u3057\u305f\u3002\u4ee5\u4e0b\u306e\u30c4\u30a4\u30fc\u30c8\u306f\u3054\u304f\u3054\u304f\u79c1\u7684\u306a\u3082\u306e\u3067\u3059\u3002", "entities": {"description": {"urls": []}, "url": {"urls": [{"display_url": "asahi.com", "expanded_url": "http://www.asahi.com/", "url": "http://t.co/ZYbBnTHg5F", "indices": [0, 22]}]}}, "fast_followers_count": 0, "favourites_count": 21, "followers_count": 2469, "friends_count": 815, "has_custom_timelines": false, "is_translator": false, "listed_count": 88, "location": "Tokyo", "media_count": 210, "name": "\u5c71\u4e2d\u5b63\u5e83", "normal_followers_count": 2469, "pinned_tweet_ids_str": [], "possibly_sensitive": false, "profile_banner_url": "https://pbs.twimg.com/profile_banners/1515867654/1442978361", "profile_image_url_https": "https://pbs.twimg.com/profile_images/515460519684100096/gXuNxE15_normal.jpeg", "profile_interstitial_type": "", "screen_name": "ymnk_t", "statuses_count": 965, "translator_type": "none", "url": "http://t.co/ZYbBnTHg5F", "verified": false, "want_retweets": false, "withheld_in_countries": []}}}, "userDisplayType": "User"}, "clientEventInfo": {"component": "FollowingSgs", "element": "user"}}}, {"entryId": "user-34598159", "sortIndex": "1725702210483911726", "content": {"entryType": "TimelineTimelineItem", "__typename": "TimelineTimelineItem", "itemContent": {"itemType": "TimelineUser", "__typename": "TimelineUser", "user_results": {"result": {"__typename": "User", "id": "VXNlcjozNDU5ODE1OQ==", "rest_id": "34598159", "affiliates_highlighted_label": {}, "has_graduated_access": true, "is_blue_verified": false, "profile_image_shape": "Circle", "legacy": {"can_dm": false, "can_media_tag": true, "created_at": "Thu Apr 23 12:27:57 +0000 2009", "default_profile": false, "default_profile_image": false, "description": "Worried. Welsh Australian. This is my personal account.", "entities": {"description": {"urls": []}}, "fast_followers_count": 0, "favourites_count": 255, "followers_count": 935, "friends_count": 847, "has_custom_timelines": true, "is_translator": false, "listed_count": 44, "location": "London, England", "media_count": 105, "name": "Simon Morris", "normal_followers_count": 935, "pinned_tweet_ids_str": [], "possibly_sensitive": false, "profile_banner_url": "https://pbs.twimg.com/profile_banners/34598159/1697470372", "profile_image_url_https": "https://pbs.twimg.com/profile_images/1219272842837209088/XAFREwut_normal.jpg", "profile_interstitial_type": "", "screen_name": "SimonMorrised", "statuses_count": 3721, "translator_type": "none", "verified": false, "want_retweets": false, "withheld_in_countries": []}}}, "userDisplayType": "User"}, "clientEventInfo": {"component": "FollowingSgs", "element": "user"}}}, {"entryId": "user-149689194", "sortIndex": "1725702210483911725", "content": {"entryType": "TimelineTimelineItem", "__typename": "TimelineTimelineItem", "itemContent": {"itemType": "TimelineUser", "__typename": "TimelineUser", "user_results": {"result": {"__typename": "User", "id": "VXNlcjoxNDk2ODkxOTQ=", "rest_id": "149689194", "affiliates_highlighted_label": {}, "has_graduated_access": true, "is_blue_verified": false, "profile_image_shape": "Circle", "legacy": {"can_dm": false, "can_media_tag": true, "created_at": "Sat May 29 23:54:22 +0000 2010", "default_profile": true, "default_profile_image": false, "description": "Non Bullshit Innovation (Penguin). WIRED UK founding editor. Investor Grammarly Improbable Cerebral Kitopi. Community at https://t.co/9jj3LMlfuN. david(at)https://t.co/tCqngABba3", "entities": {"description": {"urls": [{"display_url": "VOYAGERS.io", "expanded_url": "http://VOYAGERS.io", "url": "https://t.co/9jj3LMlfuN", "indices": [121, 144]}, {"display_url": "davidrowan.com", "expanded_url": "http://davidrowan.com", "url": "https://t.co/tCqngABba3", "indices": [155, 178]}]}, "url": {"urls": [{"display_url": "davidrowan.com", "expanded_url": "http://davidrowan.com", "url": "https://t.co/tCqngABba3", "indices": [0, 23]}]}}, "fast_followers_count": 0, "favourites_count": 619, "followers_count": 28926, "friends_count": 922, "has_custom_timelines": true, "is_translator": false, "listed_count": 1243, "location": "London", "media_count": 112, "name": "David Rowan", "normal_followers_count": 28926, "pinned_tweet_ids_str": ["1128968230763155456"], "possibly_sensitive": false, "profile_banner_url": "https://pbs.twimg.com/profile_banners/149689194/1564216420", "profile_image_url_https": "https://pbs.twimg.com/profile_images/1155033494336212992/KKnUfYU0_normal.jpg", "profile_interstitial_type": "", "screen_name": "iRowan", "statuses_count": 4160, "translator_type": "none", "url": "https://t.co/tCqngABba3", "verified": false, "want_retweets": false, "withheld_in_countries": []}}}, "userDisplayType": "User"}, "clientEventInfo": {"component": "FollowingSgs", "element": "user"}}}, {"entryId": "user-20704445", "sortIndex": "1725702210483911724", "content": {"entryType": "TimelineTimelineItem", "__typename": "TimelineTimelineItem", "itemContent": {"itemType": "TimelineUser", "__typename": "TimelineUser", "user_results": {"result": {"__typename": "User", "id": "VXNlcjoyMDcwNDQ0NQ==", "rest_id": "20704445", "affiliates_highlighted_label": {}, "has_graduated_access": true, "is_blue_verified": false, "profile_image_shape": "Circle", "legacy": {"can_dm": true, "can_media_tag": true, "created_at": "Thu Feb 12 18:57:07 +0000 2009", "default_profile": false, "default_profile_image": false, "description": "Turkey correspondent at the @FinancialTimes. adam.samson@ft.com.", "entities": {"description": {"urls": []}, "url": {"urls": [{"display_url": "ft.com", "expanded_url": "https://www.ft.com", "url": "https://t.co/Yrpx997fpB", "indices": [0, 23]}]}}, "fast_followers_count": 0, "favourites_count": 5684, "followers_count": 13326, "friends_count": 3642, "has_custom_timelines": true, "is_translator": false, "listed_count": 379, "location": "Ankara, T\u00fcrkiye", "media_count": 1676, "name": "Adam Samson", "normal_followers_count": 13326, "pinned_tweet_ids_str": [], "possibly_sensitive": false, "profile_banner_url": "https://pbs.twimg.com/profile_banners/20704445/1676881818", "profile_image_url_https": "https://pbs.twimg.com/profile_images/1318574996554473475/PZIbj3PZ_normal.jpg", "profile_interstitial_type": "", "screen_name": "adamsamson", "statuses_count": 15376, "translator_type": "none", "url": "https://t.co/Yrpx997fpB", "verified": false, "want_retweets": false, "withheld_in_countries": []}}}, "userDisplayType": "User"}, "clientEventInfo": {"component": "FollowingSgs", "element": "user"}}}, {"entryId": "user-250868109", "sortIndex": "1725702210483911723", "content": {"entryType": "TimelineTimelineItem", "__typename": "TimelineTimelineItem", "itemContent": {"itemType": "TimelineUser", "__typename": "TimelineUser", "user_results": {"result": {"__typename": "User", "id": "VXNlcjoyNTA4NjgxMDk=", "rest_id": "250868109", "affiliates_highlighted_label": {}, "has_graduated_access": true, "is_blue_verified": false, "profile_image_shape": "Circle", "legacy": {"can_dm": false, "can_media_tag": true, "created_at": "Fri Feb 11 23:53:28 +0000 2011", "default_profile": false, "default_profile_image": false, "description": "Jersey Girl*Former journalist @ WPBF, WXII, KAMC*World Traveler*Book Worm*History nerd*Proud Mom & Wife - Links & RTs \ud83d\udeab endorsements. Opinions are mine!", "entities": {"description": {"urls": []}}, "fast_followers_count": 0, "favourites_count": 2886, "followers_count": 4633, "friends_count": 4313, "has_custom_timelines": true, "is_translator": false, "listed_count": 184, "location": "Winston-Salem, NC", "media_count": 3381, "name": "Stephanie Berzinski", "normal_followers_count": 4633, "pinned_tweet_ids_str": [], "possibly_sensitive": false, "profile_banner_url": "https://pbs.twimg.com/profile_banners/250868109/1620326942", "profile_image_url_https": "https://pbs.twimg.com/profile_images/988930299412271104/NJaExK7V_normal.jpg", "profile_interstitial_type": "", "screen_name": "SBerzinski", "statuses_count": 45132, "translator_type": "none", "verified": false, "want_retweets": false, "withheld_in_countries": []}}}, "userDisplayType": "User"}, "clientEventInfo": {"component": "FollowingSgs", "element": "user"}}}, {"entryId": "user-19241553", "sortIndex": "1725702210483911722", "content": {"entryType": "TimelineTimelineItem", "__typename": "TimelineTimelineItem", "itemContent": {"itemType": "TimelineUser", "__typename": "TimelineUser", "user_results": {"result": {"__typename": "User", "id": "VXNlcjoxOTI0MTU1Mw==", "rest_id": "19241553", "affiliates_highlighted_label": {}, "has_graduated_access": true, "is_blue_verified": false, "profile_image_shape": "Circle", "legacy": {"can_dm": true, "can_media_tag": true, "created_at": "Tue Jan 20 15:43:23 +0000 2009", "default_profile": false, "default_profile_image": false, "description": "Carbon-based language model generating Science and Technology content at Sky News", "entities": {"description": {"urls": []}, "url": {"urls": [{"display_url": "news.sky.com", "expanded_url": "http://news.sky.com", "url": "https://t.co/DWuXJpS7Gj", "indices": [0, 23]}]}}, "fast_followers_count": 0, "favourites_count": 4511, "followers_count": 11047, "friends_count": 2602, "has_custom_timelines": true, "is_translator": false, "listed_count": 299, "location": "London, England", "media_count": 536, "name": "Tom Clarke", "normal_followers_count": 11047, "pinned_tweet_ids_str": [], "possibly_sensitive": false, "profile_banner_url": "https://pbs.twimg.com/profile_banners/19241553/1679937611", "profile_image_url_https": "https://pbs.twimg.com/profile_images/1640403199583567877/MzX0iGwN_normal.jpg", "profile_interstitial_type": "", "screen_name": "t0mclark3", "statuses_count": 9652, "translator_type": "none", "url": "https://t.co/DWuXJpS7Gj", "verified": false, "want_retweets": false, "withheld_in_countries": []}}}, "userDisplayType": "User"}, "clientEventInfo": {"component": "FollowingSgs", "element": "user"}}}, {"entryId": "user-84445191", "sortIndex": "1725702210483911721", "content": {"entryType": "TimelineTimelineItem", "__typename": "TimelineTimelineItem", "itemContent": {"itemType": "TimelineUser", "__typename": "TimelineUser", "user_results": {"result": {"__typename": "User", "id": "VXNlcjo4NDQ0NTE5MQ==", "rest_id": "84445191", "affiliates_highlighted_label": {}, "has_graduated_access": true, "is_blue_verified": false, "profile_image_shape": "Circle", "legacy": {"can_dm": false, "can_media_tag": true, "created_at": "Thu Oct 22 22:51:02 +0000 2009", "default_profile": true, "default_profile_image": false, "description": "Editorial director @voxdotcom, for Future Perfect, tech/climate and world teams. Author of END TIMES. Email bryan.walsh@vox.com", "entities": {"description": {"urls": []}, "url": {"urls": [{"display_url": "endtimesthebook.com", "expanded_url": "http://www.endtimesthebook.com", "url": "https://t.co/uKcJdQ34SZ", "indices": [0, 23]}]}}, "fast_followers_count": 0, "favourites_count": 1267, "followers_count": 21589, "friends_count": 1951, "has_custom_timelines": true, "is_translator": false, "listed_count": 1201, "location": "New York", "media_count": 42, "name": "Bryan Walsh", "normal_followers_count": 21589, "pinned_tweet_ids_str": ["1656326112283090946"], "possibly_sensitive": false, "profile_banner_url": "https://pbs.twimg.com/profile_banners/84445191/1556026943", "profile_image_url_https": "https://pbs.twimg.com/profile_images/459073846390177792/LM6sAN8-_normal.jpeg", "profile_interstitial_type": "", "screen_name": "bryanrwalsh", "statuses_count": 2938, "translator_type": "none", "url": "https://t.co/uKcJdQ34SZ", "verified": false, "want_retweets": false, "withheld_in_countries": []}, "professional": {"rest_id": "1553042445989969921", "professional_type": "Creator", "category": [{"id": 580, "name": "Media & News Company", "icon_name": "IconBriefcaseStroke"}]}}}, "userDisplayType": "User"}, "clientEventInfo": {"component": "FollowingSgs", "element": "user"}}}, {"entryId": "user-15819763", "sortIndex": "1725702210483911720", "content": {"entryType": "TimelineTimelineItem", "__typename": "TimelineTimelineItem", "itemContent": {"itemType": "TimelineUser", "__typename": "TimelineUser", "user_results": {"result": {"__typename": "User", "id": "VXNlcjoxNTgxOTc2Mw==", "rest_id": "15819763", "affiliates_highlighted_label": {}, "has_graduated_access": true, "is_blue_verified": false, "profile_image_shape": "Circle", "legacy": {"can_dm": true, "can_media_tag": true, "created_at": "Tue Aug 12 07:16:45 +0000 2008", "default_profile": true, "default_profile_image": false, "description": "Deputy news editor @GuardianAus. Formerly journalist and columnist with the @SMH. Right on top of that Rose!", "entities": {"description": {"urls": []}, "url": {"urls": [{"display_url": "theguardian.com/au", "expanded_url": "https://www.theguardian.com/au", "url": "https://t.co/SGYVdcW8hg", "indices": [0, 23]}]}}, "fast_followers_count": 0, "favourites_count": 46315, "followers_count": 22095, "friends_count": 4498, "has_custom_timelines": true, "is_translator": false, "listed_count": 363, "location": "Sydney", "media_count": 779, "name": "Josephine Tovey", "normal_followers_count": 22095, "pinned_tweet_ids_str": [], "possibly_sensitive": false, "profile_banner_url": "https://pbs.twimg.com/profile_banners/15819763/1541016963", "profile_image_url_https": "https://pbs.twimg.com/profile_images/1431177506854293504/4JY91KDt_normal.jpg", "profile_interstitial_type": "", "screen_name": "Jo_Tovey", "statuses_count": 22522, "translator_type": "none", "url": "https://t.co/SGYVdcW8hg", "verified": false, "want_retweets": false, "withheld_in_countries": []}}}, "userDisplayType": "User"}, "clientEventInfo": {"component": "FollowingSgs", "element": "user"}}}, {"entryId": "user-97703815", "sortIndex": "1725702210483911719", "content": {"entryType": "TimelineTimelineItem", "__typename": "TimelineTimelineItem", "itemContent": {"itemType": "TimelineUser", "__typename": "TimelineUser", "user_results": {"result": {"__typename": "User", "id": "VXNlcjo5NzcwMzgxNQ==", "rest_id": "97703815", "affiliates_highlighted_label": {}, "has_graduated_access": true, "is_blue_verified": false, "profile_image_shape": "Circle", "legacy": {"can_dm": false, "can_media_tag": true, "created_at": "Fri Dec 18 16:45:03 +0000 2009", "default_profile": true, "default_profile_image": false, "description": "I do graphics @WSJ. I like photography, stats, baseball, my wife Cindy Price, and two sons. Not in that order.", "entities": {"description": {"urls": []}}, "fast_followers_count": 0, "favourites_count": 886, "followers_count": 2251, "friends_count": 1251, "has_custom_timelines": false, "is_translator": false, "listed_count": 83, "location": "Maplewood, NJ", "media_count": 701, "name": "Taylor Umlauf", "normal_followers_count": 2251, "pinned_tweet_ids_str": [], "possibly_sensitive": false, "profile_banner_url": "https://pbs.twimg.com/profile_banners/97703815/1403468637", "profile_image_url_https": "https://pbs.twimg.com/profile_images/480808612915212290/fB7WGD01_normal.jpeg", "profile_interstitial_type": "", "screen_name": "TaylorUmlauf", "statuses_count": 1230, "translator_type": "none", "verified": false, "want_retweets": false, "withheld_in_countries": []}}}, "userDisplayType": "User"}, "clientEventInfo": {"component": "FollowingSgs", "element": "user"}}}, {"entryId": "cursor-bottom-1725702210483911718", "sortIndex": "1725702210483911718", "content": {"entryType": "TimelineTimelineCursor", "__typename": "TimelineTimelineCursor", "value": "1529045889510434655|1725702210483911716", "cursorType": "Bottom"}}, {"entryId": "cursor-top-1725702210483911769", "sortIndex": "1725702210483911769", "content": {"entryType": "TimelineTimelineCursor", "__typename": "TimelineTimelineCursor", "value": "-1|1725702210483911769", "cursorType": "Top"}}]}]}}}}}}